{
    "armature": {
        "joints": ["Root", "Thigh_R", "Leg_R", "Knee_R", "Thigh_L", "Leg_L", "Knee_L", "Torso", "Chest", "Head", "Shoulder_R", "Arm_R", "Hand_R", "Tool_R", "Elbow_R", "Shoulder_L", "Arm_L", "Hand_L", "Tool_L", "Elbow_L", "IK-Thigh_R", "IK-Leg_R", "IK-Thigh_L"],
        "hierarchy": [
            {
                "name": "Root",
                "transform": [1.0, 0.0, 0.0, -5e-06, 0.0, 0.0, -1.0, 0.000946, 0.0, 1.0, 0.0, 0.763972, 0.0, 0.0, 0.0, 1.0],
                "children": [
                    {
                        "name": "Thigh_R",
                        "transform": [1.0, -0.0, -0.0, 0.124994, -0.0, -0.999984, 0.00567, -0.002831, -0.0, -0.00567, -0.999984, -1.2e-05, 0.0, 0.0, 0.0, 1.0],
                        "children": [
                            {
                                "name": "Leg_R",
                                "transform": [1.0, 0.0, 1e-06, -0.0, -0.0, 0.999936, 0.011335, 0.374726, -1e-06, -0.011335, 0.999936, 0.0, 0.0, 0.0, 0.0, 1.0],
                                "children": []
                            },
                            {
                                "name": "Knee_R",
                                "transform": [1.0, 0.0, -0.0, -0.0, -0.0, 0.00567, -0.999984, 0.374726, -0.0, 0.999984, 0.00567, 0.0, 0.0, 0.0, 0.0, 1.0],
                                "children": []
                            }
                        ]
                    },
                    {
                        "name": "Thigh_L",
                        "transform": [1.0, -0.0, -0.0, -0.125006, -0.0, -0.999984, 0.00567, -0.002831, -0.0, -0.00567, -0.999984, -1.2e-05, 0.0, 0.0, 0.0, 1.0],
                        "children": [
                            {
                                "name": "Leg_L",
                                "transform": [1.0, 0.0, 1e-06, -0.0, -0.0, 0.999936, 0.011335, 0.374726, -1e-06, -0.011335, 0.999936, -0.0, 0.0, 0.0, 0.0, 1.0],
                                "children": []
                            },
                            {
                                "name": "Knee_L",
                                "transform": [1.0, 0.0, -0.0, -0.0, -0.0, 0.00567, -0.999984, 0.374726, -0.0, 0.999984, 0.00567, -0.0, 0.0, 0.0, 0.0, 1.0],
                                "children": []
                            }
                        ]
                    },
                    {
                        "name": "Torso",
                        "transform": [1.0, 0.0, 0.0, 0.0, 0.0, 1.0, 0.0, 0.05, 0.0, 0.0, 1.0, 0.0, 0.0, 0.0, 0.0, 1.0],
                        "children": [
                            {
                                "name": "Chest",
                                "transform": [1.0, 0.0, 0.0, 0.0, 0.0, 1.0, 0.0, 0.3, 0.0, 0.0, 1.0, 0.0, 0.0, 0.0, 0.0, 1.0],
                                "children": [
                                    {
                                        "name": "Head",
                                        "transform": [1.0, 0.0, 0.0, 0.0, 0.0, 1.0, 0.0, 0.4, 0.0, 0.0, 1.0, 0.0, 0.0, 0.0, 0.0, 1.0],
                                        "children": []
                                    },
                                    {
                                        "name": "Shoulder_R",
                                        "transform": [0.0, 0.952114, 0.305743, 0.0, 0.0, -0.305743, 0.952114, 0.4, 1.0, 0.0, -0.0, 0.0, 0.0, 0.0, 0.0, 1.0],
                                        "children": [
                                            {
                                                "name": "Arm_R",
                                                "transform": [0.0, 0.003946, -0.999992, -0.0, 0.952114, 0.305741, 0.001207, 0.39386, 0.305743, -0.952107, -0.003757, 0.0, 0.0, 0.0, 0.0, 1.0],
                                                "children": [
                                                    {
                                                        "name": "Hand_R",
                                                        "transform": [1.0, -0.0, 0.0, 0.0, 0.0, 0.999963, -0.008633, 0.300003, -0.0, 0.008633, 0.999963, 0.0, 0.0, 0.0, 0.0, 1.0],
                                                        "children": [
                                                            {
                                                                "name": "Tool_R",
                                                                "transform": [1.0, -0.0, 0.0, 0.0, 0.0, -0.999559, -0.029689, 0.271711, 0.0, 0.029689, -0.999559, -0.028915, 0.0, 0.0, 0.0, 1.0],
                                                                "children": []
                                                            }
                                                        ]
                                                    },
                                                    {
                                                        "name": "Elbow_R",
                                                        "transform": [-1.0, 0.0, -0.0, 0.0, 0.0, 0.003946, -0.999992, 0.300008, -0.0, -0.999992, -0.003946, -0.001252, 0.0, 0.0, 0.0, 1.0],
                                                        "children": []
                                                    }
                                                ]
                                            }
                                        ]
                                    },
                                    {
                                        "name": "Shoulder_L",
                                        "transform": [-0.0, -0.952114, -0.305743, 0.0, 0.0, -0.305743, 0.952114, 0.4, -1.0, 0.0, 0.0, 0.0, 0.0, 0.0, 0.0, 1.0],
                                        "children": [
                                            {
                                                "name": "Arm_L",
                                                "transform": [-0.0, -0.003946, 0.999992, -0.0, -0.952114, 0.305741, 0.001206, 0.39386, -0.305743, -0.952106, -0.003757, 0.0, 0.0, 0.0, 0.0, 1.0],
                                                "children": [
                                                    {
                                                        "name": "Hand_L",
                                                        "transform": [1.0, -0.0, 0.0, -0.0, 0.0, 0.999963, -0.008633, 0.300003, -0.0, 0.008633, 0.999963, -0.0, 0.0, 0.0, 0.0, 1.0],
                                                        "children": [
                                                            {
                                                                "name": "Tool_L",
                                                                "transform": [1.0, -0.0, 0.0, -0.0, 0.0, -0.999559, -0.029689, 0.271711, 0.0, 0.029689, -0.999559, -0.028915, 0.0, 0.0, 0.0, 1.0],
                                                                "children": []
                                                            }
                                                        ]
                                                    },
                                                    {
                                                        "name": "Elbow_L",
                                                        "transform": [-1.0, 0.0, -0.0, -0.0, 0.0, 0.003946, -0.999992, 0.300008, -0.0, -0.999992, -0.003946, -0.001252, 0.0, 0.0, 0.0, 1.0],
                                                        "children": []
                                                    }
                                                ]
                                            }
                                        ]
                                    }
                                ]
                            }
                        ]
                    },
                    {
                        "name": "IK-Thigh_R",
                        "transform": [1.0, -0.0, -0.0, 0.124994, -0.0, -0.999984, 0.00567, -0.002831, -0.0, -0.00567, -0.999984, -1.2e-05, 0.0, 0.0, 0.0, 1.0],
                        "children": [
                            {
                                "name": "IK-Leg_R",
                                "transform": [1.0, 0.0, 1e-06, -0.0, -0.0, 0.999936, 0.011335, 0.374726, -1e-06, -0.011335, 0.999936, 0.0, 0.0, 0.0, 0.0, 1.0],
                                "children": []
                            }
                        ]
                    },
                    {
                        "name": "IK-Thigh_L",
                        "transform": [1.0, -0.0, -0.0, -0.125006, -0.0, -0.999984, 0.00567, -0.002831, -0.0, -0.00567, -0.999984, -1.2e-05, 0.0, 0.0, 0.0, 1.0],
                        "children": []
                    }
                ]
            },
            {},
            {},
            {},
            {},
            {},
            {},
            {},
            {}
        ]
    },
    "animation": [
        {
            "name": "Root",
            "time": [0.0, 0.0333, 0.0667, 0.1, 0.1333, 0.1667, 0.2, 0.2333, 0.2667, 0.3, 0.3333, 0.3667, 0.4, 0.4333, 0.4667, 0.5, 0.5333, 0.5667, 0.6, 0.6333, 0.6667, 0.7, 0.7333, 0.7667, 0.8, 0.8333, 0.8667, 0.9, 0.9333, 0.9667, 1.0],
            "transform": [
                [1.0, 0.0, 0.0, -5e-06, 0.0, 0.0, -1.0, 0.000946, 0.0, 1.0, 0.0, 0.763972, 0.0, 0.0, 0.0, 1.0],
                [1.0, 0.0, 0.0, -5e-06, 0.0, 0.0, -1.0, 0.000946, 0.0, 1.0, 0.0, 0.763972, 0.0, 0.0, 0.0, 1.0],
                [1.0, 0.0, 0.0, -5e-06, 0.0, 0.0, -1.0, 0.000946, 0.0, 1.0, 0.0, 0.763972, 0.0, 0.0, 0.0, 1.0],
                [1.0, 0.0, 0.0, -5e-06, 0.0, 0.0, -1.0, 0.000946, 0.0, 1.0, 0.0, 0.763972, 0.0, 0.0, 0.0, 1.0],
                [1.0, 0.0, 0.0, -5e-06, 0.0, 0.0, -1.0, 0.000946, 0.0, 1.0, 0.0, 0.763972, 0.0, 0.0, 0.0, 1.0],
                [1.0, 0.0, 0.0, -5e-06, 0.0, 0.0, -1.0, 0.000946, 0.0, 1.0, 0.0, 0.763972, 0.0, 0.0, 0.0, 1.0],
                [1.0, 0.0, 0.0, -5e-06, 0.0, 0.0, -1.0, 0.000946, 0.0, 1.0, 0.0, 0.763972, 0.0, 0.0, 0.0, 1.0],
                [1.0, 0.0, 0.0, -5e-06, 0.0, 0.0, -1.0, 0.000946, 0.0, 1.0, 0.0, 0.763972, 0.0, 0.0, 0.0, 1.0],
                [1.0, 0.0, 0.0, -5e-06, 0.0, 0.0, -1.0, 0.000946, 0.0, 1.0, 0.0, 0.763972, 0.0, 0.0, 0.0, 1.0],
                [1.0, 0.0, 0.0, -5e-06, 0.0, 0.0, -1.0, 0.000946, 0.0, 1.0, 0.0, 0.763972, 0.0, 0.0, 0.0, 1.0],
                [1.0, 0.0, 0.0, -5e-06, 0.0, 0.0, -1.0, 0.000946, 0.0, 1.0, 0.0, 0.763972, 0.0, 0.0, 0.0, 1.0],
                [1.0, 0.0, 0.0, -5e-06, 0.0, 0.0, -1.0, 0.000946, 0.0, 1.0, 0.0, 0.763972, 0.0, 0.0, 0.0, 1.0],
                [1.0, 0.0, 0.0, -5e-06, 0.0, 0.0, -1.0, 0.000946, 0.0, 1.0, 0.0, 0.763972, 0.0, 0.0, 0.0, 1.0],
                [1.0, 0.0, 0.0, -5e-06, 0.0, 0.0, -1.0, 0.000946, 0.0, 1.0, 0.0, 0.763972, 0.0, 0.0, 0.0, 1.0],
                [1.0, 0.0, 0.0, -5e-06, 0.0, 0.0, -1.0, 0.000946, 0.0, 1.0, 0.0, 0.763972, 0.0, 0.0, 0.0, 1.0],
                [1.0, 0.0, 0.0, -5e-06, 0.0, 0.0, -1.0, 0.000946, 0.0, 1.0, 0.0, 0.763972, 0.0, 0.0, 0.0, 1.0],
                [1.0, 0.0, 0.0, -5e-06, 0.0, 0.0, -1.0, 0.000946, 0.0, 1.0, 0.0, 0.763972, 0.0, 0.0, 0.0, 1.0],
                [1.0, 0.0, 0.0, -5e-06, 0.0, 0.0, -1.0, 0.000946, 0.0, 1.0, 0.0, 0.763972, 0.0, 0.0, 0.0, 1.0],
                [1.0, 0.0, 0.0, -5e-06, 0.0, 0.0, -1.0, 0.000946, 0.0, 1.0, 0.0, 0.763972, 0.0, 0.0, 0.0, 1.0],
                [1.0, 0.0, 0.0, -5e-06, 0.0, 0.0, -1.0, 0.000946, 0.0, 1.0, 0.0, 0.763972, 0.0, 0.0, 0.0, 1.0],
                [1.0, 0.0, 0.0, -5e-06, 0.0, 0.0, -1.0, 0.000946, 0.0, 1.0, 0.0, 0.763972, 0.0, 0.0, 0.0, 1.0],
                [1.0, 0.0, 0.0, -5e-06, 0.0, 0.0, -1.0, 0.000946, 0.0, 1.0, 0.0, 0.763972, 0.0, 0.0, 0.0, 1.0],
                [1.0, 0.0, 0.0, -5e-06, 0.0, 0.0, -1.0, 0.000946, 0.0, 1.0, 0.0, 0.763972, 0.0, 0.0, 0.0, 1.0],
                [1.0, 0.0, 0.0, -5e-06, 0.0, 0.0, -1.0, 0.000946, 0.0, 1.0, 0.0, 0.763972, 0.0, 0.0, 0.0, 1.0],
                [1.0, 0.0, 0.0, -5e-06, 0.0, 0.0, -1.0, 0.000946, 0.0, 1.0, 0.0, 0.763972, 0.0, 0.0, 0.0, 1.0],
                [1.0, 0.0, 0.0, -5e-06, 0.0, 0.0, -1.0, 0.000946, 0.0, 1.0, 0.0, 0.763972, 0.0, 0.0, 0.0, 1.0],
                [1.0, 0.0, 0.0, -5e-06, 0.0, 0.0, -1.0, 0.000946, 0.0, 1.0, 0.0, 0.763972, 0.0, 0.0, 0.0, 1.0],
                [1.0, 0.0, 0.0, -5e-06, 0.0, 0.0, -1.0, 0.000946, 0.0, 1.0, 0.0, 0.763972, 0.0, 0.0, 0.0, 1.0],
                [1.0, 0.0, 0.0, -5e-06, 0.0, 0.0, -1.0, 0.000946, 0.0, 1.0, 0.0, 0.763972, 0.0, 0.0, 0.0, 1.0],
                [1.0, 0.0, 0.0, -5e-06, 0.0, 0.0, -1.0, 0.000946, 0.0, 1.0, 0.0, 0.763972, 0.0, 0.0, 0.0, 1.0],
                [1.0, 0.0, 0.0, -5e-06, 0.0, 0.0, -1.0, 0.000946, 0.0, 1.0, 0.0, 0.763972, 0.0, 0.0, 0.0, 1.0]
            ]
        },
        {
            "name": "Thigh_R",
            "time": [0.0, 0.0333, 0.0667, 0.1, 0.1333, 0.1667, 0.2, 0.2333, 0.2667, 0.3, 0.3333, 0.3667, 0.4, 0.4333, 0.4667, 0.5, 0.5333, 0.5667, 0.6, 0.6333, 0.6667, 0.7, 0.7333, 0.7667, 0.8, 0.8333, 0.8667, 0.9, 0.9333, 0.9667, 1.0],
            "transform": [
                [1.0, -0.0, -0.0, 0.124994, -0.0, -0.999984, 0.005946, -0.002831, -0.0, -0.005946, -0.999982, -1.2e-05, 0.0, 0.0, 0.0, 1.0],
                [1.0, -0.0, -0.0, 0.124994, -0.0, -0.999984, 0.005946, -0.002831, -0.0, -0.005946, -0.999982, -1.2e-05, 0.0, 0.0, 0.0, 1.0],
                [1.0, -0.0, -0.0, 0.124994, -0.0, -0.999984, 0.005946, -0.002831, -0.0, -0.005946, -0.999982, -1.2e-05, 0.0, 0.0, 0.0, 1.0],
                [1.0, -0.0, -0.0, 0.124994, -0.0, -0.999984, 0.005946, -0.002831, -0.0, -0.005946, -0.999982, -1.2e-05, 0.0, 0.0, 0.0, 1.0],
                [1.0, -0.0, -0.0, 0.124994, -0.0, -0.999984, 0.005946, -0.002831, -0.0, -0.005946, -0.999982, -1.2e-05, 0.0, 0.0, 0.0, 1.0],
                [1.0, -0.0, -0.0, 0.124994, -0.0, -0.999984, 0.005946, -0.002831, -0.0, -0.005946, -0.999982, -1.2e-05, 0.0, 0.0, 0.0, 1.0],
                [1.0, -0.0, -0.0, 0.124994, -0.0, -0.999984, 0.005946, -0.002831, -0.0, -0.005946, -0.999982, -1.2e-05, 0.0, 0.0, 0.0, 1.0],
                [1.0, -0.0, -0.0, 0.124994, -0.0, -0.999984, 0.005946, -0.002831, -0.0, -0.005946, -0.999982, -1.2e-05, 0.0, 0.0, 0.0, 1.0],
                [1.0, -0.0, -0.0, 0.124994, -0.0, -0.999984, 0.005946, -0.002831, -0.0, -0.005946, -0.999982, -1.2e-05, 0.0, 0.0, 0.0, 1.0],
                [1.0, -0.0, -0.0, 0.124994, -0.0, -0.999984, 0.005946, -0.002831, -0.0, -0.005946, -0.999982, -1.2e-05, 0.0, 0.0, 0.0, 1.0],
                [1.0, -0.0, -0.0, 0.124994, -0.0, -0.999984, 0.005946, -0.002831, -0.0, -0.005946, -0.999982, -1.2e-05, 0.0, 0.0, 0.0, 1.0],
                [1.0, -0.0, -0.0, 0.124994, -0.0, -0.999984, 0.005946, -0.002831, -0.0, -0.005946, -0.999982, -1.2e-05, 0.0, 0.0, 0.0, 1.0],
                [1.0, -0.0, -0.0, 0.124994, -0.0, -0.999984, 0.005946, -0.002831, -0.0, -0.005946, -0.999982, -1.2e-05, 0.0, 0.0, 0.0, 1.0],
                [1.0, -0.0, -0.0, 0.124994, -0.0, -0.999984, 0.005946, -0.002831, -0.0, -0.005946, -0.999982, -1.2e-05, 0.0, 0.0, 0.0, 1.0],
                [1.0, -0.0, -0.0, 0.124994, -0.0, -0.999984, 0.005946, -0.002831, -0.0, -0.005946, -0.999982, -1.2e-05, 0.0, 0.0, 0.0, 1.0],
                [1.0, -0.0, -0.0, 0.124994, -0.0, -0.999984, 0.005946, -0.002831, -0.0, -0.005946, -0.999982, -1.2e-05, 0.0, 0.0, 0.0, 1.0],
                [1.0, -0.0, -0.0, 0.124994, -0.0, -0.999984, 0.005946, -0.002831, -0.0, -0.005946, -0.999982, -1.2e-05, 0.0, 0.0, 0.0, 1.0],
                [1.0, -0.0, -0.0, 0.124994, -0.0, -0.999984, 0.005946, -0.002831, -0.0, -0.005946, -0.999982, -1.2e-05, 0.0, 0.0, 0.0, 1.0],
                [1.0, -0.0, -0.0, 0.124994, -0.0, -0.999984, 0.005946, -0.002831, -0.0, -0.005946, -0.999982, -1.2e-05, 0.0, 0.0, 0.0, 1.0],
                [1.0, -0.0, -0.0, 0.124994, -0.0, -0.999984, 0.005946, -0.002831, -0.0, -0.005946, -0.999982, -1.2e-05, 0.0, 0.0, 0.0, 1.0],
                [1.0, -0.0, -0.0, 0.124994, -0.0, -0.999984, 0.005946, -0.002831, -0.0, -0.005946, -0.999982, -1.2e-05, 0.0, 0.0, 0.0, 1.0],
                [1.0, -0.0, -0.0, 0.124994, -0.0, -0.999984, 0.005946, -0.002831, -0.0, -0.005946, -0.999982, -1.2e-05, 0.0, 0.0, 0.0, 1.0],
                [1.0, -0.0, -0.0, 0.124994, -0.0, -0.999984, 0.005946, -0.002831, -0.0, -0.005946, -0.999982, -1.2e-05, 0.0, 0.0, 0.0, 1.0],
                [1.0, -0.0, -0.0, 0.124994, -0.0, -0.999984, 0.005946, -0.002831, -0.0, -0.005946, -0.999982, -1.2e-05, 0.0, 0.0, 0.0, 1.0],
                [1.0, -0.0, -0.0, 0.124994, -0.0, -0.999984, 0.005946, -0.002831, -0.0, -0.005946, -0.999982, -1.2e-05, 0.0, 0.0, 0.0, 1.0],
                [1.0, -0.0, -0.0, 0.124994, -0.0, -0.999984, 0.005946, -0.002831, -0.0, -0.005946, -0.999982, -1.2e-05, 0.0, 0.0, 0.0, 1.0],
                [1.0, -0.0, -0.0, 0.124994, -0.0, -0.999984, 0.005946, -0.002831, -0.0, -0.005946, -0.999982, -1.2e-05, 0.0, 0.0, 0.0, 1.0],
                [1.0, -0.0, -0.0, 0.124994, -0.0, -0.999984, 0.005946, -0.002831, -0.0, -0.005946, -0.999982, -1.2e-05, 0.0, 0.0, 0.0, 1.0],
                [1.0, -0.0, -0.0, 0.124994, -0.0, -0.999984, 0.005946, -0.002831, -0.0, -0.005946, -0.999982, -1.2e-05, 0.0, 0.0, 0.0, 1.0],
                [1.0, -0.0, -0.0, 0.124994, -0.0, -0.999984, 0.005946, -0.002831, -0.0, -0.005946, -0.999982, -1.2e-05, 0.0, 0.0, 0.0, 1.0],
                [1.0, -0.0, -0.0, 0.124994, -0.0, -0.999984, 0.005946, -0.002831, -0.0, -0.005946, -0.999982, -1.2e-05, 0.0, 0.0, 0.0, 1.0]
            ]
        },
        {
            "name": "Leg_R",
            "time": [0.0, 0.0333, 0.0667, 0.1, 0.1333, 0.1667, 0.2, 0.2333, 0.2667, 0.3, 0.3333, 0.3667, 0.4, 0.4333, 0.4667, 0.5, 0.5333, 0.5667, 0.6, 0.6333, 0.6667, 0.7, 0.7333, 0.7667, 0.8, 0.8333, 0.8667, 0.9, 0.9333, 0.9667, 1.0],
            "transform": [
                [1.0, 0.0, 1e-06, 0.0, -0.0, 0.999929, 0.011887, 0.374726, -1e-06, -0.011887, 0.999929, -0.0, 0.0, 0.0, 0.0, 1.0],
                [1.0, 0.0, 1e-06, 0.0, -0.0, 0.999929, 0.011887, 0.374726, -1e-06, -0.011887, 0.999929, -0.0, 0.0, 0.0, 0.0, 1.0],
                [1.0, 0.0, 1e-06, 0.0, -0.0, 0.999929, 0.011887, 0.374726, -1e-06, -0.011887, 0.999929, -0.0, 0.0, 0.0, 0.0, 1.0],
                [1.0, 0.0, 1e-06, 0.0, -0.0, 0.999929, 0.011887, 0.374726, -1e-06, -0.011887, 0.999929, -0.0, 0.0, 0.0, 0.0, 1.0],
                [1.0, 0.0, 1e-06, 0.0, -0.0, 0.999929, 0.011887, 0.374726, -1e-06, -0.011887, 0.999929, -0.0, 0.0, 0.0, 0.0, 1.0],
                [1.0, 0.0, 1e-06, 0.0, -0.0, 0.999929, 0.011887, 0.374726, -1e-06, -0.011887, 0.999929, -0.0, 0.0, 0.0, 0.0, 1.0],
                [1.0, 0.0, 1e-06, 0.0, -0.0, 0.999929, 0.011887, 0.374726, -1e-06, -0.011887, 0.999929, -0.0, 0.0, 0.0, 0.0, 1.0],
                [1.0, 0.0, 1e-06, 0.0, -0.0, 0.999929, 0.011887, 0.374726, -1e-06, -0.011887, 0.999929, -0.0, 0.0, 0.0, 0.0, 1.0],
                [1.0, 0.0, 1e-06, 0.0, -0.0, 0.999929, 0.011887, 0.374726, -1e-06, -0.011887, 0.999929, -0.0, 0.0, 0.0, 0.0, 1.0],
                [1.0, 0.0, 1e-06, 0.0, -0.0, 0.999929, 0.011887, 0.374726, -1e-06, -0.011887, 0.999929, -0.0, 0.0, 0.0, 0.0, 1.0],
                [1.0, 0.0, 1e-06, 0.0, -0.0, 0.999929, 0.011887, 0.374726, -1e-06, -0.011887, 0.999929, -0.0, 0.0, 0.0, 0.0, 1.0],
                [1.0, 0.0, 1e-06, 0.0, -0.0, 0.999929, 0.011887, 0.374726, -1e-06, -0.011887, 0.999929, -0.0, 0.0, 0.0, 0.0, 1.0],
                [1.0, 0.0, 1e-06, 0.0, -0.0, 0.999929, 0.011887, 0.374726, -1e-06, -0.011887, 0.999929, -0.0, 0.0, 0.0, 0.0, 1.0],
                [1.0, 0.0, 1e-06, 0.0, -0.0, 0.999929, 0.011887, 0.374726, -1e-06, -0.011887, 0.999929, -0.0, 0.0, 0.0, 0.0, 1.0],
                [1.0, 0.0, 1e-06, 0.0, -0.0, 0.999929, 0.011887, 0.374726, -1e-06, -0.011887, 0.999929, -0.0, 0.0, 0.0, 0.0, 1.0],
                [1.0, 0.0, 1e-06, 0.0, -0.0, 0.999929, 0.011887, 0.374726, -1e-06, -0.011887, 0.999929, -0.0, 0.0, 0.0, 0.0, 1.0],
                [1.0, 0.0, 1e-06, 0.0, -0.0, 0.999929, 0.011887, 0.374726, -1e-06, -0.011887, 0.999929, -0.0, 0.0, 0.0, 0.0, 1.0],
                [1.0, 0.0, 1e-06, 0.0, -0.0, 0.999929, 0.011887, 0.374726, -1e-06, -0.011887, 0.999929, -0.0, 0.0, 0.0, 0.0, 1.0],
                [1.0, 0.0, 1e-06, 0.0, -0.0, 0.999929, 0.011887, 0.374726, -1e-06, -0.011887, 0.999929, -0.0, 0.0, 0.0, 0.0, 1.0],
                [1.0, 0.0, 1e-06, 0.0, -0.0, 0.999929, 0.011887, 0.374726, -1e-06, -0.011887, 0.999929, -0.0, 0.0, 0.0, 0.0, 1.0],
                [1.0, 0.0, 1e-06, 0.0, -0.0, 0.999929, 0.011887, 0.374726, -1e-06, -0.011887, 0.999929, -0.0, 0.0, 0.0, 0.0, 1.0],
                [1.0, 0.0, 1e-06, 0.0, -0.0, 0.999929, 0.011887, 0.374726, -1e-06, -0.011887, 0.999929, -0.0, 0.0, 0.0, 0.0, 1.0],
                [1.0, 0.0, 1e-06, 0.0, -0.0, 0.999929, 0.011887, 0.374726, -1e-06, -0.011887, 0.999929, -0.0, 0.0, 0.0, 0.0, 1.0],
                [1.0, 0.0, 1e-06, 0.0, -0.0, 0.999929, 0.011887, 0.374726, -1e-06, -0.011887, 0.999929, -0.0, 0.0, 0.0, 0.0, 1.0],
                [1.0, 0.0, 1e-06, 0.0, -0.0, 0.999929, 0.011887, 0.374726, -1e-06, -0.011887, 0.999929, -0.0, 0.0, 0.0, 0.0, 1.0],
                [1.0, 0.0, 1e-06, 0.0, -0.0, 0.999929, 0.011887, 0.374726, -1e-06, -0.011887, 0.999929, -0.0, 0.0, 0.0, 0.0, 1.0],
                [1.0, 0.0, 1e-06, 0.0, -0.0, 0.999929, 0.011887, 0.374726, -1e-06, -0.011887, 0.999929, -0.0, 0.0, 0.0, 0.0, 1.0],
                [1.0, 0.0, 1e-06, 0.0, -0.0, 0.999929, 0.011887, 0.374726, -1e-06, -0.011887, 0.999929, -0.0, 0.0, 0.0, 0.0, 1.0],
                [1.0, 0.0, 1e-06, 0.0, -0.0, 0.999929, 0.011887, 0.374726, -1e-06, -0.011887, 0.999929, -0.0, 0.0, 0.0, 0.0, 1.0],
                [1.0, 0.0, 1e-06, 0.0, -0.0, 0.999929, 0.011887, 0.374726, -1e-06, -0.011887, 0.999929, -0.0, 0.0, 0.0, 0.0, 1.0],
                [1.0, 0.0, 1e-06, 0.0, -0.0, 0.999929, 0.011887, 0.374726, -1e-06, -0.011887, 0.999929, -0.0, 0.0, 0.0, 0.0, 1.0]
            ]
        },
        {
            "name": "Knee_R",
            "time": [0.0, 1.0],
            "transform": [
                [1.0, 0.0, -0.0, 0.0, -0.0, 0.00567, -0.999984, 0.374726, -0.0, 0.999984, 0.00567, -0.0, 0.0, 0.0, 0.0, 1.0],
                [1.0, 0.0, -0.0, 0.0, -0.0, 0.00567, -0.999984, 0.374726, -0.0, 0.999984, 0.00567, -0.0, 0.0, 0.0, 0.0, 1.0]
            ]
        },
        {
            "name": "Thigh_L",
            "time": [0.0, 0.0333, 0.0667, 0.1, 0.1333, 0.1667, 0.2, 0.2333, 0.2667, 0.3, 0.3333, 0.3667, 0.4, 0.4333, 0.4667, 0.5, 0.5333, 0.5667, 0.6, 0.6333, 0.6667, 0.7, 0.7333, 0.7667, 0.8, 0.8333, 0.8667, 0.9, 0.9333, 0.9667, 1.0],
            "transform": [
                [1.0, -0.0, -0.0, -0.125006, -0.0, -0.999984, 0.005917, -0.002831, -0.0, -0.005917, -0.999983, -1.2e-05, 0.0, 0.0, 0.0, 1.0],
                [1.0, -0.0, -0.0, -0.125006, -0.0, -0.999984, 0.005917, -0.002831, -0.0, -0.005917, -0.999983, -1.2e-05, 0.0, 0.0, 0.0, 1.0],
                [1.0, -0.0, -0.0, -0.125006, -0.0, -0.999984, 0.005917, -0.002831, -0.0, -0.005917, -0.999983, -1.2e-05, 0.0, 0.0, 0.0, 1.0],
                [1.0, -0.0, -0.0, -0.125006, -0.0, -0.999984, 0.005917, -0.002831, -0.0, -0.005917, -0.999983, -1.2e-05, 0.0, 0.0, 0.0, 1.0],
                [1.0, -0.0, -0.0, -0.125006, -0.0, -0.999984, 0.005917, -0.002831, -0.0, -0.005917, -0.999983, -1.2e-05, 0.0, 0.0, 0.0, 1.0],
                [1.0, -0.0, -0.0, -0.125006, -0.0, -0.999984, 0.005917, -0.002831, -0.0, -0.005917, -0.999983, -1.2e-05, 0.0, 0.0, 0.0, 1.0],
                [1.0, -0.0, -0.0, -0.125006, -0.0, -0.999984, 0.005917, -0.002831, -0.0, -0.005917, -0.999983, -1.2e-05, 0.0, 0.0, 0.0, 1.0],
                [1.0, -0.0, -0.0, -0.125006, -0.0, -0.999984, 0.005917, -0.002831, -0.0, -0.005917, -0.999983, -1.2e-05, 0.0, 0.0, 0.0, 1.0],
                [1.0, -0.0, -0.0, -0.125006, -0.0, -0.999984, 0.005917, -0.002831, -0.0, -0.005917, -0.999983, -1.2e-05, 0.0, 0.0, 0.0, 1.0],
                [1.0, -0.0, -0.0, -0.125006, -0.0, -0.999984, 0.005917, -0.002831, -0.0, -0.005917, -0.999983, -1.2e-05, 0.0, 0.0, 0.0, 1.0],
                [1.0, -0.0, -0.0, -0.125006, -0.0, -0.999984, 0.005917, -0.002831, -0.0, -0.005917, -0.999983, -1.2e-05, 0.0, 0.0, 0.0, 1.0],
                [1.0, -0.0, -0.0, -0.125006, -0.0, -0.999984, 0.005917, -0.002831, -0.0, -0.005917, -0.999983, -1.2e-05, 0.0, 0.0, 0.0, 1.0],
                [1.0, -0.0, -0.0, -0.125006, -0.0, -0.999984, 0.005917, -0.002831, -0.0, -0.005917, -0.999983, -1.2e-05, 0.0, 0.0, 0.0, 1.0],
                [1.0, -0.0, -0.0, -0.125006, -0.0, -0.999984, 0.005917, -0.002831, -0.0, -0.005917, -0.999983, -1.2e-05, 0.0, 0.0, 0.0, 1.0],
                [1.0, -0.0, -0.0, -0.125006, -0.0, -0.999984, 0.005917, -0.002831, -0.0, -0.005917, -0.999983, -1.2e-05, 0.0, 0.0, 0.0, 1.0],
                [1.0, -0.0, -0.0, -0.125006, -0.0, -0.999984, 0.005917, -0.002831, -0.0, -0.005917, -0.999983, -1.2e-05, 0.0, 0.0, 0.0, 1.0],
                [1.0, -0.0, -0.0, -0.125006, -0.0, -0.999984, 0.005917, -0.002831, -0.0, -0.005917, -0.999983, -1.2e-05, 0.0, 0.0, 0.0, 1.0],
                [1.0, -0.0, -0.0, -0.125006, -0.0, -0.999984, 0.005917, -0.002831, -0.0, -0.005917, -0.999983, -1.2e-05, 0.0, 0.0, 0.0, 1.0],
                [1.0, -0.0, -0.0, -0.125006, -0.0, -0.999984, 0.005917, -0.002831, -0.0, -0.005917, -0.999983, -1.2e-05, 0.0, 0.0, 0.0, 1.0],
                [1.0, -0.0, -0.0, -0.125006, -0.0, -0.999984, 0.005917, -0.002831, -0.0, -0.005917, -0.999983, -1.2e-05, 0.0, 0.0, 0.0, 1.0],
                [1.0, -0.0, -0.0, -0.125006, -0.0, -0.999984, 0.005917, -0.002831, -0.0, -0.005917, -0.999983, -1.2e-05, 0.0, 0.0, 0.0, 1.0],
                [1.0, -0.0, -0.0, -0.125006, -0.0, -0.999984, 0.005917, -0.002831, -0.0, -0.005917, -0.999983, -1.2e-05, 0.0, 0.0, 0.0, 1.0],
                [1.0, -0.0, -0.0, -0.125006, -0.0, -0.999984, 0.005917, -0.002831, -0.0, -0.005917, -0.999983, -1.2e-05, 0.0, 0.0, 0.0, 1.0],
                [1.0, -0.0, -0.0, -0.125006, -0.0, -0.999984, 0.005917, -0.002831, -0.0, -0.005917, -0.999983, -1.2e-05, 0.0, 0.0, 0.0, 1.0],
                [1.0, -0.0, -0.0, -0.125006, -0.0, -0.999984, 0.005917, -0.002831, -0.0, -0.005917, -0.999983, -1.2e-05, 0.0, 0.0, 0.0, 1.0],
                [1.0, -0.0, -0.0, -0.125006, -0.0, -0.999984, 0.005917, -0.002831, -0.0, -0.005917, -0.999983, -1.2e-05, 0.0, 0.0, 0.0, 1.0],
                [1.0, -0.0, -0.0, -0.125006, -0.0, -0.999984, 0.005917, -0.002831, -0.0, -0.005917, -0.999983, -1.2e-05, 0.0, 0.0, 0.0, 1.0],
                [1.0, -0.0, -0.0, -0.125006, -0.0, -0.999984, 0.005917, -0.002831, -0.0, -0.005917, -0.999983, -1.2e-05, 0.0, 0.0, 0.0, 1.0],
                [1.0, -0.0, -0.0, -0.125006, -0.0, -0.999984, 0.005917, -0.002831, -0.0, -0.005917, -0.999983, -1.2e-05, 0.0, 0.0, 0.0, 1.0],
                [1.0, -0.0, -0.0, -0.125006, -0.0, -0.999984, 0.005917, -0.002831, -0.0, -0.005917, -0.999983, -1.2e-05, 0.0, 0.0, 0.0, 1.0],
                [1.0, -0.0, -0.0, -0.125006, -0.0, -0.999984, 0.005917, -0.002831, -0.0, -0.005917, -0.999983, -1.2e-05, 0.0, 0.0, 0.0, 1.0]
            ]
        },
        {
            "name": "Leg_L",
            "time": [0.0, 0.0333, 0.0667, 0.1, 0.1333, 0.1667, 0.2, 0.2333, 0.2667, 0.3, 0.3333, 0.3667, 0.4, 0.4333, 0.4667, 0.5, 0.5333, 0.5667, 0.6, 0.6333, 0.6667, 0.7, 0.7333, 0.7667, 0.8, 0.8333, 0.8667, 0.9, 0.9333, 0.9667, 1.0],
            "transform": [
                [1.0, 0.0, 1e-06, -0.0, -0.0, 0.99993, 0.01183, 0.374726, -1e-06, -0.01183, 0.99993, -0.0, 0.0, 0.0, 0.0, 1.0],
                [1.0, 0.0, 1e-06, -0.0, -0.0, 0.99993, 0.01183, 0.374726, -1e-06, -0.01183, 0.99993, -0.0, 0.0, 0.0, 0.0, 1.0],
                [1.0, 0.0, 1e-06, -0.0, -0.0, 0.99993, 0.01183, 0.374726, -1e-06, -0.01183, 0.99993, -0.0, 0.0, 0.0, 0.0, 1.0],
                [1.0, 0.0, 1e-06, -0.0, -0.0, 0.99993, 0.01183, 0.374726, -1e-06, -0.01183, 0.99993, -0.0, 0.0, 0.0, 0.0, 1.0],
                [1.0, 0.0, 1e-06, -0.0, -0.0, 0.99993, 0.01183, 0.374726, -1e-06, -0.01183, 0.99993, -0.0, 0.0, 0.0, 0.0, 1.0],
                [1.0, 0.0, 1e-06, -0.0, -0.0, 0.99993, 0.01183, 0.374726, -1e-06, -0.01183, 0.99993, -0.0, 0.0, 0.0, 0.0, 1.0],
                [1.0, 0.0, 1e-06, -0.0, -0.0, 0.99993, 0.01183, 0.374726, -1e-06, -0.01183, 0.99993, -0.0, 0.0, 0.0, 0.0, 1.0],
                [1.0, 0.0, 1e-06, -0.0, -0.0, 0.99993, 0.01183, 0.374726, -1e-06, -0.01183, 0.99993, -0.0, 0.0, 0.0, 0.0, 1.0],
                [1.0, 0.0, 1e-06, -0.0, -0.0, 0.99993, 0.01183, 0.374726, -1e-06, -0.01183, 0.99993, -0.0, 0.0, 0.0, 0.0, 1.0],
                [1.0, 0.0, 1e-06, -0.0, -0.0, 0.99993, 0.01183, 0.374726, -1e-06, -0.01183, 0.99993, -0.0, 0.0, 0.0, 0.0, 1.0],
                [1.0, 0.0, 1e-06, -0.0, -0.0, 0.99993, 0.01183, 0.374726, -1e-06, -0.01183, 0.99993, -0.0, 0.0, 0.0, 0.0, 1.0],
                [1.0, 0.0, 1e-06, -0.0, -0.0, 0.99993, 0.01183, 0.374726, -1e-06, -0.01183, 0.99993, -0.0, 0.0, 0.0, 0.0, 1.0],
                [1.0, 0.0, 1e-06, -0.0, -0.0, 0.99993, 0.01183, 0.374726, -1e-06, -0.01183, 0.99993, -0.0, 0.0, 0.0, 0.0, 1.0],
                [1.0, 0.0, 1e-06, -0.0, -0.0, 0.99993, 0.01183, 0.374726, -1e-06, -0.01183, 0.99993, -0.0, 0.0, 0.0, 0.0, 1.0],
                [1.0, 0.0, 1e-06, -0.0, -0.0, 0.99993, 0.01183, 0.374726, -1e-06, -0.01183, 0.99993, -0.0, 0.0, 0.0, 0.0, 1.0],
                [1.0, 0.0, 1e-06, -0.0, -0.0, 0.99993, 0.01183, 0.374726, -1e-06, -0.01183, 0.99993, -0.0, 0.0, 0.0, 0.0, 1.0],
                [1.0, 0.0, 1e-06, -0.0, -0.0, 0.99993, 0.01183, 0.374726, -1e-06, -0.01183, 0.99993, -0.0, 0.0, 0.0, 0.0, 1.0],
                [1.0, 0.0, 1e-06, -0.0, -0.0, 0.99993, 0.01183, 0.374726, -1e-06, -0.01183, 0.99993, -0.0, 0.0, 0.0, 0.0, 1.0],
                [1.0, 0.0, 1e-06, -0.0, -0.0, 0.99993, 0.01183, 0.374726, -1e-06, -0.01183, 0.99993, -0.0, 0.0, 0.0, 0.0, 1.0],
                [1.0, 0.0, 1e-06, -0.0, -0.0, 0.99993, 0.01183, 0.374726, -1e-06, -0.01183, 0.99993, -0.0, 0.0, 0.0, 0.0, 1.0],
                [1.0, 0.0, 1e-06, -0.0, -0.0, 0.99993, 0.01183, 0.374726, -1e-06, -0.01183, 0.99993, -0.0, 0.0, 0.0, 0.0, 1.0],
                [1.0, 0.0, 1e-06, -0.0, -0.0, 0.99993, 0.01183, 0.374726, -1e-06, -0.01183, 0.99993, -0.0, 0.0, 0.0, 0.0, 1.0],
                [1.0, 0.0, 1e-06, -0.0, -0.0, 0.99993, 0.01183, 0.374726, -1e-06, -0.01183, 0.99993, -0.0, 0.0, 0.0, 0.0, 1.0],
                [1.0, 0.0, 1e-06, -0.0, -0.0, 0.99993, 0.01183, 0.374726, -1e-06, -0.01183, 0.99993, -0.0, 0.0, 0.0, 0.0, 1.0],
                [1.0, 0.0, 1e-06, -0.0, -0.0, 0.99993, 0.01183, 0.374726, -1e-06, -0.01183, 0.99993, -0.0, 0.0, 0.0, 0.0, 1.0],
                [1.0, 0.0, 1e-06, -0.0, -0.0, 0.99993, 0.01183, 0.374726, -1e-06, -0.01183, 0.99993, -0.0, 0.0, 0.0, 0.0, 1.0],
                [1.0, 0.0, 1e-06, -0.0, -0.0, 0.99993, 0.01183, 0.374726, -1e-06, -0.01183, 0.99993, -0.0, 0.0, 0.0, 0.0, 1.0],
                [1.0, 0.0, 1e-06, -0.0, -0.0, 0.99993, 0.01183, 0.374726, -1e-06, -0.01183, 0.99993, -0.0, 0.0, 0.0, 0.0, 1.0],
                [1.0, 0.0, 1e-06, -0.0, -0.0, 0.99993, 0.01183, 0.374726, -1e-06, -0.01183, 0.99993, -0.0, 0.0, 0.0, 0.0, 1.0],
                [1.0, 0.0, 1e-06, -0.0, -0.0, 0.99993, 0.01183, 0.374726, -1e-06, -0.01183, 0.99993, -0.0, 0.0, 0.0, 0.0, 1.0],
                [1.0, 0.0, 1e-06, -0.0, -0.0, 0.99993, 0.01183, 0.374726, -1e-06, -0.01183, 0.99993, -0.0, 0.0, 0.0, 0.0, 1.0]
            ]
        },
        {
            "name": "Knee_L",
            "time": [0.0, 1.0],
            "transform": [
                [1.0, 0.0, -0.0, -0.0, -0.0, 0.00567, -0.999984, 0.374726, -0.0, 0.999984, 0.00567, -0.0, 0.0, 0.0, 0.0, 1.0],
                [1.0, 0.0, -0.0, -0.0, -0.0, 0.00567, -0.999984, 0.374726, -0.0, 0.999984, 0.00567, -0.0, 0.0, 0.0, 0.0, 1.0]
            ]
        },
        {
            "name": "Torso",
            "time": [0.0, 0.0333, 0.0667, 0.1, 0.1333, 0.1667, 0.2, 0.2333, 0.2667, 0.3, 0.3333, 0.3667, 0.4, 0.4333, 0.4667, 0.5, 0.5333, 0.5667, 0.6, 0.6333, 0.6667, 0.7, 0.7333, 0.7667, 0.8, 0.8333, 0.8667, 0.9, 0.9333, 0.9667, 1.0],
            "transform": [
                [0.95795, 0.0, -0.286936, 0.0, 0.0, 1.0, 0.0, 0.05, 0.286936, 0.0, 0.95795, 0.0, 0.0, 0.0, 0.0, 1.0],
                [0.95795, 0.0, -0.286936, 0.0, 0.0, 1.0, 0.0, 0.05, 0.286936, 0.0, 0.95795, 0.0, 0.0, 0.0, 0.0, 1.0],
                [0.95795, 0.0, -0.286936, 0.0, 0.0, 1.0, 0.0, 0.05, 0.286936, 0.0, 0.95795, 0.0, 0.0, 0.0, 0.0, 1.0],
                [0.95795, 0.0, -0.286936, 0.0, 0.0, 1.0, 0.0, 0.05, 0.286936, 0.0, 0.95795, 0.0, 0.0, 0.0, 0.0, 1.0],
                [0.95795, 0.0, -0.286936, 0.0, 0.0, 1.0, 0.0, 0.05, 0.286936, 0.0, 0.95795, 0.0, 0.0, 0.0, 0.0, 1.0],
                [0.95795, 0.0, -0.286936, 0.0, 0.0, 1.0, 0.0, 0.05, 0.286936, 0.0, 0.95795, 0.0, 0.0, 0.0, 0.0, 1.0],
                [0.95795, 0.0, -0.286936, 0.0, 0.0, 1.0, 0.0, 0.05, 0.286936, 0.0, 0.95795, 0.0, 0.0, 0.0, 0.0, 1.0],
                [0.95795, 0.0, -0.286936, 0.0, 0.0, 1.0, 0.0, 0.05, 0.286936, 0.0, 0.95795, 0.0, 0.0, 0.0, 0.0, 1.0],
                [0.95795, 0.0, -0.286936, 0.0, 0.0, 1.0, 0.0, 0.05, 0.286936, 0.0, 0.95795, 0.0, 0.0, 0.0, 0.0, 1.0],
                [0.95795, 0.0, -0.286936, 0.0, 0.0, 1.0, 0.0, 0.05, 0.286936, 0.0, 0.95795, 0.0, 0.0, 0.0, 0.0, 1.0],
                [0.95795, 0.0, -0.286936, 0.0, 0.0, 1.0, 0.0, 0.05, 0.286936, 0.0, 0.95795, 0.0, 0.0, 0.0, 0.0, 1.0],
                [0.95795, 0.0, -0.286936, 0.0, 0.0, 1.0, 0.0, 0.05, 0.286936, 0.0, 0.95795, 0.0, 0.0, 0.0, 0.0, 1.0],
                [0.95795, 0.0, -0.286936, 0.0, 0.0, 1.0, 0.0, 0.05, 0.286936, 0.0, 0.95795, 0.0, 0.0, 0.0, 0.0, 1.0],
                [0.95795, 0.0, -0.286936, 0.0, 0.0, 1.0, 0.0, 0.05, 0.286936, 0.0, 0.95795, 0.0, 0.0, 0.0, 0.0, 1.0],
                [0.95795, 0.0, -0.286936, 0.0, 0.0, 1.0, 0.0, 0.05, 0.286936, 0.0, 0.95795, 0.0, 0.0, 0.0, 0.0, 1.0],
                [0.95795, 0.0, -0.286936, 0.0, 0.0, 1.0, 0.0, 0.05, 0.286936, 0.0, 0.95795, 0.0, 0.0, 0.0, 0.0, 1.0],
                [0.95795, 0.0, -0.286936, 0.0, 0.0, 1.0, 0.0, 0.05, 0.286936, 0.0, 0.95795, 0.0, 0.0, 0.0, 0.0, 1.0],
                [0.95795, 0.0, -0.286936, 0.0, 0.0, 1.0, 0.0, 0.05, 0.286936, 0.0, 0.95795, 0.0, 0.0, 0.0, 0.0, 1.0],
                [0.95795, 0.0, -0.286936, 0.0, 0.0, 1.0, 0.0, 0.05, 0.286936, 0.0, 0.95795, 0.0, 0.0, 0.0, 0.0, 1.0],
                [0.95795, 0.0, -0.286936, 0.0, 0.0, 1.0, 0.0, 0.05, 0.286936, 0.0, 0.95795, 0.0, 0.0, 0.0, 0.0, 1.0],
                [0.95795, 0.0, -0.286936, 0.0, 0.0, 1.0, 0.0, 0.05, 0.286936, 0.0, 0.95795, 0.0, 0.0, 0.0, 0.0, 1.0],
                [0.95795, 0.0, -0.286936, 0.0, 0.0, 1.0, 0.0, 0.05, 0.286936, 0.0, 0.95795, 0.0, 0.0, 0.0, 0.0, 1.0],
                [0.95795, 0.0, -0.286936, 0.0, 0.0, 1.0, 0.0, 0.05, 0.286936, 0.0, 0.95795, 0.0, 0.0, 0.0, 0.0, 1.0],
                [0.95795, 0.0, -0.286936, 0.0, 0.0, 1.0, 0.0, 0.05, 0.286936, 0.0, 0.95795, 0.0, 0.0, 0.0, 0.0, 1.0],
                [0.95795, 0.0, -0.286936, 0.0, 0.0, 1.0, 0.0, 0.05, 0.286936, 0.0, 0.95795, 0.0, 0.0, 0.0, 0.0, 1.0],
                [0.95795, 0.0, -0.286936, 0.0, 0.0, 1.0, 0.0, 0.05, 0.286936, 0.0, 0.95795, 0.0, 0.0, 0.0, 0.0, 1.0],
                [0.95795, 0.0, -0.286936, 0.0, 0.0, 1.0, 0.0, 0.05, 0.286936, 0.0, 0.95795, 0.0, 0.0, 0.0, 0.0, 1.0],
                [0.95795, 0.0, -0.286936, 0.0, 0.0, 1.0, 0.0, 0.05, 0.286936, 0.0, 0.95795, 0.0, 0.0, 0.0, 0.0, 1.0],
                [0.95795, 0.0, -0.286936, 0.0, 0.0, 1.0, 0.0, 0.05, 0.286936, 0.0, 0.95795, 0.0, 0.0, 0.0, 0.0, 1.0],
                [0.95795, 0.0, -0.286936, 0.0, 0.0, 1.0, 0.0, 0.05, 0.286936, 0.0, 0.95795, 0.0, 0.0, 0.0, 0.0, 1.0],
                [0.95795, 0.0, -0.286936, 0.0, 0.0, 1.0, 0.0, 0.05, 0.286936, 0.0, 0.95795, 0.0, 0.0, 0.0, 0.0, 1.0]
            ]
        },
        {
            "name": "Chest",
            "time": [0.0, 0.0333, 0.0667, 0.1, 0.1333, 0.1667, 0.2, 0.2333, 0.2667, 0.3, 0.3333, 0.3667, 0.4, 0.4333, 0.4667, 0.5, 0.5333, 0.5667, 0.6, 0.6333, 0.6667, 0.7, 0.7333, 0.7667, 0.8, 0.8333, 0.8667, 0.9, 0.9333, 0.9667, 1.0],
            "transform": [
                [1.0, 0.0, 0.0, -0.0, 0.0, 1.0, 0.0, 0.3, 0.0, 0.0, 1.0, -0.0, 0.0, 0.0, 0.0, 1.0],
                [1.0, 0.0, 0.0, -0.0, 0.0, 1.0, 0.0, 0.3, 0.0, 0.0, 1.0, -0.0, 0.0, 0.0, 0.0, 1.0],
                [1.0, 0.0, 0.0, -0.0, 0.0, 1.0, 0.0, 0.3, 0.0, 0.0, 1.0, -0.0, 0.0, 0.0, 0.0, 1.0],
                [1.0, 0.0, 0.0, -0.0, 0.0, 1.0, 0.0, 0.3, 0.0, 0.0, 1.0, -0.0, 0.0, 0.0, 0.0, 1.0],
                [1.0, 0.0, 0.0, -0.0, 0.0, 1.0, 0.0, 0.3, 0.0, 0.0, 1.0, -0.0, 0.0, 0.0, 0.0, 1.0],
                [1.0, 0.0, 0.0, -0.0, 0.0, 1.0, 0.0, 0.3, 0.0, 0.0, 1.0, -0.0, 0.0, 0.0, 0.0, 1.0],
                [1.0, 0.0, 0.0, -0.0, 0.0, 1.0, 0.0, 0.3, 0.0, 0.0, 1.0, -0.0, 0.0, 0.0, 0.0, 1.0],
                [1.0, 0.0, 0.0, -0.0, 0.0, 1.0, 0.0, 0.3, 0.0, 0.0, 1.0, -0.0, 0.0, 0.0, 0.0, 1.0],
                [1.0, 0.0, 0.0, -0.0, 0.0, 1.0, 0.0, 0.3, 0.0, 0.0, 1.0, -0.0, 0.0, 0.0, 0.0, 1.0],
                [1.0, 0.0, 0.0, -0.0, 0.0, 1.0, 0.0, 0.3, 0.0, 0.0, 1.0, -0.0, 0.0, 0.0, 0.0, 1.0],
                [1.0, 0.0, 0.0, -0.0, 0.0, 1.0, 0.0, 0.3, 0.0, 0.0, 1.0, -0.0, 0.0, 0.0, 0.0, 1.0],
                [1.0, 0.0, 0.0, -0.0, 0.0, 1.0, 0.0, 0.3, 0.0, 0.0, 1.0, -0.0, 0.0, 0.0, 0.0, 1.0],
                [1.0, 0.0, 0.0, -0.0, 0.0, 1.0, 0.0, 0.3, 0.0, 0.0, 1.0, -0.0, 0.0, 0.0, 0.0, 1.0],
                [1.0, 0.0, 0.0, -0.0, 0.0, 1.0, 0.0, 0.3, 0.0, 0.0, 1.0, -0.0, 0.0, 0.0, 0.0, 1.0],
                [1.0, 0.0, 0.0, -0.0, 0.0, 1.0, 0.0, 0.3, 0.0, 0.0, 1.0, -0.0, 0.0, 0.0, 0.0, 1.0],
                [1.0, 0.0, 0.0, -0.0, 0.0, 1.0, 0.0, 0.3, 0.0, 0.0, 1.0, -0.0, 0.0, 0.0, 0.0, 1.0],
                [1.0, 0.0, 0.0, -0.0, 0.0, 1.0, 0.0, 0.3, 0.0, 0.0, 1.0, -0.0, 0.0, 0.0, 0.0, 1.0],
                [1.0, 0.0, 0.0, -0.0, 0.0, 1.0, 0.0, 0.3, 0.0, 0.0, 1.0, -0.0, 0.0, 0.0, 0.0, 1.0],
                [1.0, 0.0, 0.0, -0.0, 0.0, 1.0, 0.0, 0.3, 0.0, 0.0, 1.0, -0.0, 0.0, 0.0, 0.0, 1.0],
                [1.0, 0.0, 0.0, -0.0, 0.0, 1.0, 0.0, 0.3, 0.0, 0.0, 1.0, -0.0, 0.0, 0.0, 0.0, 1.0],
                [1.0, 0.0, 0.0, -0.0, 0.0, 1.0, 0.0, 0.3, 0.0, 0.0, 1.0, -0.0, 0.0, 0.0, 0.0, 1.0],
                [1.0, 0.0, 0.0, -0.0, 0.0, 1.0, 0.0, 0.3, 0.0, 0.0, 1.0, -0.0, 0.0, 0.0, 0.0, 1.0],
                [1.0, 0.0, 0.0, -0.0, 0.0, 1.0, 0.0, 0.3, 0.0, 0.0, 1.0, -0.0, 0.0, 0.0, 0.0, 1.0],
                [1.0, 0.0, 0.0, -0.0, 0.0, 1.0, 0.0, 0.3, 0.0, 0.0, 1.0, -0.0, 0.0, 0.0, 0.0, 1.0],
                [1.0, 0.0, 0.0, -0.0, 0.0, 1.0, 0.0, 0.3, 0.0, 0.0, 1.0, -0.0, 0.0, 0.0, 0.0, 1.0],
                [1.0, 0.0, 0.0, -0.0, 0.0, 1.0, 0.0, 0.3, 0.0, 0.0, 1.0, -0.0, 0.0, 0.0, 0.0, 1.0],
                [1.0, 0.0, 0.0, -0.0, 0.0, 1.0, 0.0, 0.3, 0.0, 0.0, 1.0, -0.0, 0.0, 0.0, 0.0, 1.0],
                [1.0, 0.0, 0.0, -0.0, 0.0, 1.0, 0.0, 0.3, 0.0, 0.0, 1.0, -0.0, 0.0, 0.0, 0.0, 1.0],
                [1.0, 0.0, 0.0, -0.0, 0.0, 1.0, 0.0, 0.3, 0.0, 0.0, 1.0, -0.0, 0.0, 0.0, 0.0, 1.0],
                [1.0, 0.0, 0.0, -0.0, 0.0, 1.0, 0.0, 0.3, 0.0, 0.0, 1.0, -0.0, 0.0, 0.0, 0.0, 1.0],
                [1.0, 0.0, 0.0, -0.0, 0.0, 1.0, 0.0, 0.3, 0.0, 0.0, 1.0, -0.0, 0.0, 0.0, 0.0, 1.0]
            ]
        },
        {
            "name": "Head",
            "time": [0.0, 0.0333, 0.0667, 0.1, 0.1333, 0.1667, 0.2, 0.2333, 0.2667, 0.3, 0.3333, 0.3667, 0.4, 0.4333, 0.4667, 0.5, 0.5333, 0.5667, 0.6, 0.6333, 0.6667, 0.7, 0.7333, 0.7667, 0.8, 0.8333, 0.8667, 0.9, 0.9333, 0.9667, 1.0],
            "transform": [
                [0.95869, 0.0, 0.284455, -0.0, 0.0, 1.0, 0.0, 0.4, -0.284455, 0.0, 0.958689, -0.0, 0.0, 0.0, 0.0, 1.0],
                [0.95869, 0.0, 0.284455, -0.0, 0.0, 1.0, 0.0, 0.4, -0.284455, 0.0, 0.958689, -0.0, 0.0, 0.0, 0.0, 1.0],
                [0.95869, 0.0, 0.284455, -0.0, 0.0, 1.0, 0.0, 0.4, -0.284455, 0.0, 0.958689, -0.0, 0.0, 0.0, 0.0, 1.0],
                [0.95869, 0.0, 0.284455, -0.0, 0.0, 1.0, 0.0, 0.4, -0.284455, 0.0, 0.958689, -0.0, 0.0, 0.0, 0.0, 1.0],
                [0.95869, 0.0, 0.284455, -0.0, 0.0, 1.0, 0.0, 0.4, -0.284455, 0.0, 0.958689, -0.0, 0.0, 0.0, 0.0, 1.0],
                [0.95869, 0.0, 0.284455, -0.0, 0.0, 1.0, 0.0, 0.4, -0.284455, 0.0, 0.958689, -0.0, 0.0, 0.0, 0.0, 1.0],
                [0.95869, 0.0, 0.284455, -0.0, 0.0, 1.0, 0.0, 0.4, -0.284455, 0.0, 0.958689, -0.0, 0.0, 0.0, 0.0, 1.0],
                [0.95869, 0.0, 0.284455, -0.0, 0.0, 1.0, 0.0, 0.4, -0.284455, 0.0, 0.958689, -0.0, 0.0, 0.0, 0.0, 1.0],
                [0.95869, 0.0, 0.284455, -0.0, 0.0, 1.0, 0.0, 0.4, -0.284455, 0.0, 0.958689, -0.0, 0.0, 0.0, 0.0, 1.0],
                [0.95869, 0.0, 0.284455, -0.0, 0.0, 1.0, 0.0, 0.4, -0.284455, 0.0, 0.958689, -0.0, 0.0, 0.0, 0.0, 1.0],
                [0.95869, 0.0, 0.284455, -0.0, 0.0, 1.0, 0.0, 0.4, -0.284455, 0.0, 0.958689, -0.0, 0.0, 0.0, 0.0, 1.0],
                [0.95869, 0.0, 0.284455, -0.0, 0.0, 1.0, 0.0, 0.4, -0.284455, 0.0, 0.958689, -0.0, 0.0, 0.0, 0.0, 1.0],
                [0.95869, 0.0, 0.284455, -0.0, 0.0, 1.0, 0.0, 0.4, -0.284455, 0.0, 0.958689, -0.0, 0.0, 0.0, 0.0, 1.0],
                [0.95869, 0.0, 0.284455, -0.0, 0.0, 1.0, 0.0, 0.4, -0.284455, 0.0, 0.958689, -0.0, 0.0, 0.0, 0.0, 1.0],
                [0.95869, 0.0, 0.284455, -0.0, 0.0, 1.0, 0.0, 0.4, -0.284455, 0.0, 0.958689, -0.0, 0.0, 0.0, 0.0, 1.0],
                [0.95869, 0.0, 0.284455, -0.0, 0.0, 1.0, 0.0, 0.4, -0.284455, 0.0, 0.958689, -0.0, 0.0, 0.0, 0.0, 1.0],
                [0.95869, 0.0, 0.284455, -0.0, 0.0, 1.0, 0.0, 0.4, -0.284455, 0.0, 0.958689, -0.0, 0.0, 0.0, 0.0, 1.0],
                [0.95869, 0.0, 0.284455, -0.0, 0.0, 1.0, 0.0, 0.4, -0.284455, 0.0, 0.958689, -0.0, 0.0, 0.0, 0.0, 1.0],
                [0.95869, 0.0, 0.284455, -0.0, 0.0, 1.0, 0.0, 0.4, -0.284455, 0.0, 0.958689, -0.0, 0.0, 0.0, 0.0, 1.0],
                [0.95869, 0.0, 0.284455, -0.0, 0.0, 1.0, 0.0, 0.4, -0.284455, 0.0, 0.958689, -0.0, 0.0, 0.0, 0.0, 1.0],
                [0.95869, 0.0, 0.284455, -0.0, 0.0, 1.0, 0.0, 0.4, -0.284455, 0.0, 0.958689, -0.0, 0.0, 0.0, 0.0, 1.0],
                [0.95869, 0.0, 0.284455, -0.0, 0.0, 1.0, 0.0, 0.4, -0.284455, 0.0, 0.958689, -0.0, 0.0, 0.0, 0.0, 1.0],
                [0.95869, 0.0, 0.284455, -0.0, 0.0, 1.0, 0.0, 0.4, -0.284455, 0.0, 0.958689, -0.0, 0.0, 0.0, 0.0, 1.0],
                [0.95869, 0.0, 0.284455, -0.0, 0.0, 1.0, 0.0, 0.4, -0.284455, 0.0, 0.958689, -0.0, 0.0, 0.0, 0.0, 1.0],
                [0.95869, 0.0, 0.284455, -0.0, 0.0, 1.0, 0.0, 0.4, -0.284455, 0.0, 0.958689, -0.0, 0.0, 0.0, 0.0, 1.0],
                [0.95869, 0.0, 0.284455, -0.0, 0.0, 1.0, 0.0, 0.4, -0.284455, 0.0, 0.958689, -0.0, 0.0, 0.0, 0.0, 1.0],
                [0.95869, 0.0, 0.284455, -0.0, 0.0, 1.0, 0.0, 0.4, -0.284455, 0.0, 0.958689, -0.0, 0.0, 0.0, 0.0, 1.0],
                [0.95869, 0.0, 0.284455, -0.0, 0.0, 1.0, 0.0, 0.4, -0.284455, 0.0, 0.958689, -0.0, 0.0, 0.0, 0.0, 1.0],
                [0.95869, 0.0, 0.284455, -0.0, 0.0, 1.0, 0.0, 0.4, -0.284455, 0.0, 0.958689, -0.0, 0.0, 0.0, 0.0, 1.0],
                [0.95869, 0.0, 0.284455, -0.0, 0.0, 1.0, 0.0, 0.4, -0.284455, 0.0, 0.958689, -0.0, 0.0, 0.0, 0.0, 1.0],
                [0.95869, 0.0, 0.284455, -0.0, 0.0, 1.0, 0.0, 0.4, -0.284455, 0.0, 0.958689, -0.0, 0.0, 0.0, 0.0, 1.0]
            ]
        },
        {
            "name": "Shoulder_R",
            "time": [0.0, 0.0333, 0.0667, 0.1, 0.1333, 0.1667, 0.2, 0.2333, 0.2667, 0.3, 0.3333, 0.3667, 0.4, 0.4333, 0.4667, 0.5, 0.5333, 0.5667, 0.6, 0.6333, 0.6667, 0.7, 0.7333, 0.7667, 0.8, 0.8333, 0.8667, 0.9, 0.9333, 0.9667, 1.0],
            "transform": [
                [0.0, 0.952114, 0.305743, 0.0, 0.0, -0.305743, 0.952114, 0.4, 1.0, 0.0, -0.0, 0.0, 0.0, 0.0, 0.0, 1.0],
                [0.0, 0.952114, 0.305743, 0.0, 0.0, -0.305743, 0.952114, 0.4, 1.0, 0.0, -0.0, 0.0, 0.0, 0.0, 0.0, 1.0],
                [0.0, 0.952114, 0.305743, 0.0, 0.0, -0.305743, 0.952114, 0.4, 1.0, 0.0, -0.0, 0.0, 0.0, 0.0, 0.0, 1.0],
                [0.0, 0.952114, 0.305743, 0.0, 0.0, -0.305743, 0.952114, 0.4, 1.0, 0.0, -0.0, 0.0, 0.0, 0.0, 0.0, 1.0],
                [0.0, 0.952114, 0.305743, 0.0, 0.0, -0.305743, 0.952114, 0.4, 1.0, 0.0, -0.0, 0.0, 0.0, 0.0, 0.0, 1.0],
                [0.0, 0.952114, 0.305743, 0.0, 0.0, -0.305743, 0.952114, 0.4, 1.0, 0.0, -0.0, 0.0, 0.0, 0.0, 0.0, 1.0],
                [0.0, 0.952114, 0.305743, 0.0, 0.0, -0.305743, 0.952114, 0.4, 1.0, 0.0, -0.0, 0.0, 0.0, 0.0, 0.0, 1.0],
                [0.0, 0.952114, 0.305743, 0.0, 0.0, -0.305743, 0.952114, 0.4, 1.0, 0.0, -0.0, 0.0, 0.0, 0.0, 0.0, 1.0],
                [0.0, 0.952114, 0.305743, 0.0, 0.0, -0.305743, 0.952114, 0.4, 1.0, 0.0, -0.0, 0.0, 0.0, 0.0, 0.0, 1.0],
                [0.0, 0.952114, 0.305743, 0.0, 0.0, -0.305743, 0.952114, 0.4, 1.0, 0.0, -0.0, 0.0, 0.0, 0.0, 0.0, 1.0],
                [0.0, 0.952114, 0.305743, 0.0, 0.0, -0.305743, 0.952114, 0.4, 1.0, 0.0, -0.0, 0.0, 0.0, 0.0, 0.0, 1.0],
                [0.0, 0.952114, 0.305743, 0.0, 0.0, -0.305743, 0.952114, 0.4, 1.0, 0.0, -0.0, 0.0, 0.0, 0.0, 0.0, 1.0],
                [0.0, 0.952114, 0.305743, 0.0, 0.0, -0.305743, 0.952114, 0.4, 1.0, 0.0, -0.0, 0.0, 0.0, 0.0, 0.0, 1.0],
                [0.0, 0.952114, 0.305743, 0.0, 0.0, -0.305743, 0.952114, 0.4, 1.0, 0.0, -0.0, 0.0, 0.0, 0.0, 0.0, 1.0],
                [0.0, 0.952114, 0.305743, 0.0, 0.0, -0.305743, 0.952114, 0.4, 1.0, 0.0, -0.0, 0.0, 0.0, 0.0, 0.0, 1.0],
                [0.0, 0.952114, 0.305743, 0.0, 0.0, -0.305743, 0.952114, 0.4, 1.0, 0.0, -0.0, 0.0, 0.0, 0.0, 0.0, 1.0],
                [0.0, 0.952114, 0.305743, 0.0, 0.0, -0.305743, 0.952114, 0.4, 1.0, 0.0, -0.0, 0.0, 0.0, 0.0, 0.0, 1.0],
                [0.0, 0.952114, 0.305743, 0.0, 0.0, -0.305743, 0.952114, 0.4, 1.0, 0.0, -0.0, 0.0, 0.0, 0.0, 0.0, 1.0],
                [0.0, 0.952114, 0.305743, 0.0, 0.0, -0.305743, 0.952114, 0.4, 1.0, 0.0, -0.0, 0.0, 0.0, 0.0, 0.0, 1.0],
                [0.0, 0.952114, 0.305743, 0.0, 0.0, -0.305743, 0.952114, 0.4, 1.0, 0.0, -0.0, 0.0, 0.0, 0.0, 0.0, 1.0],
                [0.0, 0.952114, 0.305743, 0.0, 0.0, -0.305743, 0.952114, 0.4, 1.0, 0.0, -0.0, 0.0, 0.0, 0.0, 0.0, 1.0],
                [0.0, 0.952114, 0.305743, 0.0, 0.0, -0.305743, 0.952114, 0.4, 1.0, 0.0, -0.0, 0.0, 0.0, 0.0, 0.0, 1.0],
                [0.0, 0.952114, 0.305743, 0.0, 0.0, -0.305743, 0.952114, 0.4, 1.0, 0.0, -0.0, 0.0, 0.0, 0.0, 0.0, 1.0],
                [0.0, 0.952114, 0.305743, 0.0, 0.0, -0.305743, 0.952114, 0.4, 1.0, 0.0, -0.0, 0.0, 0.0, 0.0, 0.0, 1.0],
                [0.0, 0.952114, 0.305743, 0.0, 0.0, -0.305743, 0.952114, 0.4, 1.0, 0.0, -0.0, 0.0, 0.0, 0.0, 0.0, 1.0],
                [0.0, 0.952114, 0.305743, 0.0, 0.0, -0.305743, 0.952114, 0.4, 1.0, 0.0, -0.0, 0.0, 0.0, 0.0, 0.0, 1.0],
                [0.0, 0.952114, 0.305743, 0.0, 0.0, -0.305743, 0.952114, 0.4, 1.0, 0.0, -0.0, 0.0, 0.0, 0.0, 0.0, 1.0],
                [0.0, 0.952114, 0.305743, 0.0, 0.0, -0.305743, 0.952114, 0.4, 1.0, 0.0, -0.0, 0.0, 0.0, 0.0, 0.0, 1.0],
                [0.0, 0.952114, 0.305743, 0.0, 0.0, -0.305743, 0.952114, 0.4, 1.0, 0.0, -0.0, 0.0, 0.0, 0.0, 0.0, 1.0],
                [0.0, 0.952114, 0.305743, 0.0, 0.0, -0.305743, 0.952114, 0.4, 1.0, 0.0, -0.0, 0.0, 0.0, 0.0, 0.0, 1.0],
                [0.0, 0.952114, 0.305743, 0.0, 0.0, -0.305743, 0.952114, 0.4, 1.0, 0.0, -0.0, 0.0, 0.0, 0.0, 0.0, 1.0]
            ]
        },
        {
            "name": "Arm_R",
            "time": [0.0, 0.0333, 0.0667, 0.1, 0.1333, 0.1667, 0.2, 0.2333, 0.2667, 0.3, 0.3333, 0.3667, 0.4, 0.4333, 0.4667, 0.5, 0.5333, 0.5667, 0.6, 0.6333, 0.6667, 0.7, 0.7333, 0.7667, 0.8, 0.8333, 0.8667, 0.9, 0.9333, 0.9667, 1.0],
            "transform": [
                [0.143577, -0.410587, -0.900447, -0.0, 0.902752, 0.427148, -0.050827, 0.393861, 0.405493, -0.805583, 0.431986, 0.0, 0.0, 0.0, 0.0, 1.0],
                [0.147409, -0.403105, -0.903204, -0.0, 0.900655, 0.432107, -0.045859, 0.393861, 0.408767, -0.806716, 0.426755, 0.0, 0.0, 0.0, 0.0, 1.0],
                [0.145284, -0.400801, -0.904573, -0.0, 0.901821, 0.429701, -0.045551, 0.393861, 0.406953, -0.809145, 0.423879, 0.0, 0.0, 0.0, 0.0, 1.0],
                [0.142834, -0.407428, -0.901999, -0.0, 0.903155, 0.426439, -0.049604, 0.393861, 0.404857, -0.80756, 0.428881, 0.0, 0.0, 0.0, 0.0, 1.0],
                [0.13901, -0.416122, -0.898621, -0.0, 0.905212, 0.421374, -0.055094, 0.393861, 0.401581, -0.805784, 0.435253, 0.0, 0.0, 0.0, 0.0, 1.0],
                [0.136886, -0.420287, -0.897007, -0.0, 0.906342, 0.418572, -0.057808, 0.393861, 0.399758, -0.805082, 0.43822, 0.0, 0.0, 0.0, 0.0, 1.0],
                [0.140438, -0.416689, -0.898136, -0.0, 0.904447, 0.423045, -0.054846, 0.393861, 0.402806, -0.804614, 0.436284, 0.0, 0.0, 0.0, 0.0, 1.0],
                [0.144262, -0.411387, -0.899972, -0.0, 0.902379, 0.42792, -0.050958, 0.393861, 0.40608, -0.804765, 0.432959, 0.0, 0.0, 0.0, 0.0, 1.0],
                [0.142037, -0.405154, -0.903148, -0.0, 0.903586, 0.425615, -0.048826, 0.393861, 0.404175, -0.809137, 0.426544, 0.0, 0.0, 0.0, 0.0, 1.0],
                [0.137899, -0.404305, -0.904169, -0.0, 0.905804, 0.420737, -0.049987, 0.393861, 0.400627, -0.812107, 0.42424, 0.0, 0.0, 0.0, 0.0, 1.0],
                [0.138561, -0.408672, -0.902102, -0.0, 0.905452, 0.42128, -0.051773, 0.393861, 0.401196, -0.809636, 0.428406, 0.0, 0.0, 0.0, 0.0, 1.0],
                [0.138855, -0.411615, -0.900718, -0.0, 0.905294, 0.42146, -0.05304, 0.393861, 0.401448, -0.80805, 0.431155, 0.0, 0.0, 0.0, 0.0, 1.0],
                [0.139208, -0.415358, -0.898944, -0.0, 0.905106, 0.421657, -0.054664, 0.393861, 0.401751, -0.80603, 0.434641, 0.0, 0.0, 0.0, 0.0, 1.0],
                [0.141532, -0.417751, -0.897471, -0.0, 0.903859, 0.424287, -0.054956, 0.393861, 0.403743, -0.803409, 0.437638, 0.0, 0.0, 0.0, 0.0, 1.0],
                [0.143696, -0.414132, -0.898803, -0.0, 0.902687, 0.427087, -0.052467, 0.393861, 0.405595, -0.803799, 0.435202, 0.0, 0.0, 0.0, 0.0, 1.0],
                [0.142437, -0.406928, -0.902287, -0.0, 0.90337, 0.425994, -0.049514, 0.393861, 0.404518, -0.808047, 0.428283, 0.0, 0.0, 0.0, 0.0, 1.0],
                [0.139404, -0.406619, -0.9029, -0.0, 0.905002, 0.4224, -0.050499, 0.393861, 0.401919, -0.810086, 0.426875, 0.0, 0.0, 0.0, 0.0, 1.0],
                [0.139441, -0.415285, -0.898942, -0.0, 0.904982, 0.421939, -0.054546, 0.393861, 0.40195, -0.80592, 0.43466, 0.0, 0.0, 0.0, 0.0, 1.0],
                [0.141433, -0.422292, -0.895359, -0.0, 0.903912, 0.423884, -0.057139, 0.393861, 0.403658, -0.801244, 0.441666, 0.0, 0.0, 0.0, 0.0, 1.0],
                [0.143094, -0.423533, -0.894508, -0.0, 0.903014, 0.425792, -0.05715, 0.393861, 0.40508, -0.799576, 0.443384, 0.0, 0.0, 0.0, 0.0, 1.0],
                [0.143136, -0.421578, -0.895424, -0.0, 0.902991, 0.425967, -0.056205, 0.393861, 0.405116, -0.800515, 0.441652, 0.0, 0.0, 0.0, 0.0, 1.0],
                [0.143259, -0.423636, -0.894433, -0.0, 0.902924, 0.425984, -0.057142, 0.393861, 0.405221, -0.799419, 0.443537, 0.0, 0.0, 0.0, 0.0, 1.0],
                [0.14181, -0.418287, -0.897177, -0.0, 0.903708, 0.424587, -0.05511, 0.393861, 0.403981, -0.802971, 0.43822, 0.0, 0.0, 0.0, 0.0, 1.0],
                [0.138842, -0.407138, -0.902753, -0.0, 0.905301, 0.421702, -0.050951, 0.393861, 0.401437, -0.810189, 0.427132, 0.0, 0.0, 0.0, 0.0, 1.0],
                [0.136317, -0.399809, -0.906406, -0.0, 0.906643, 0.419099, -0.048509, 0.393861, 0.399268, -0.815174, 0.419614, 0.0, 0.0, 0.0, 0.0, 1.0],
                [0.135898, -0.398854, -0.906889, -0.0, 0.906865, 0.418652, -0.048231, 0.393861, 0.398908, -0.815872, 0.4186, 0.0, 0.0, 0.0, 0.0, 1.0],
                [0.136605, -0.39944, -0.906525, -0.0, 0.906491, 0.419461, -0.048226, 0.393861, 0.399516, -0.815169, 0.419389, 0.0, 0.0, 0.0, 0.0, 1.0],
                [0.135514, -0.396188, -0.908114, -0.0, 0.907067, 0.418336, -0.047152, 0.393861, 0.398578, -0.817331, 0.41606, 0.0, 0.0, 0.0, 0.0, 1.0],
                [0.134122, -0.396951, -0.907988, -0.0, 0.907799, 0.416643, -0.048052, 0.393861, 0.397381, -0.817826, 0.416232, 0.0, 0.0, 0.0, 0.0, 1.0],
                [0.13386, -0.404709, -0.904596, -0.0, 0.907937, 0.415903, -0.051717, 0.393861, 0.397155, -0.814393, 0.423122, 0.0, 0.0, 0.0, 0.0, 1.0],
                [0.135243, -0.407777, -0.90301, -0.0, 0.90721, 0.417376, -0.052604, 0.393861, 0.398345, -0.812106, 0.426387, 0.0, 0.0, 0.0, 0.0, 1.0]
            ]
        },
        {
            "name": "Hand_R",
            "time": [0.0, 0.0333, 0.0667, 0.1, 0.1333, 0.1667, 0.2, 0.2333, 0.2667, 0.3, 0.3333, 0.3667, 0.4, 0.4333, 0.4667, 0.5, 0.5333, 0.5667, 0.6, 0.6333, 0.6667, 0.7, 0.7333, 0.7667, 0.8, 0.8333, 0.8667, 0.9, 0.9333, 0.9667, 1.0],
            "transform": [
                [1.0, -2e-06, 1e-06, -0.0, 2e-06, 0.796782, -0.604267, 0.300003, 1e-06, 0.604267, 0.796782, -0.0, 0.0, 0.0, 0.0, 1.0],
                [1.0, -2e-06, 1e-06, -0.0, 2e-06, 0.7761, -0.63061, 0.300003, 1e-06, 0.63061, 0.7761, 0.0, 0.0, 0.0, 0.0, 1.0],
                [1.0, -2e-06, 1e-06, 0.0, 2e-06, 0.773837, -0.633385, 0.300003, 1e-06, 0.633385, 0.773837, -0.0, 0.0, 0.0, 0.0, 1.0],
                [1.0, -2e-06, 1e-06, 0.0, 2e-06, 0.791152, -0.61162, 0.300002, 1e-06, 0.61162, 0.791152, -0.0, 0.0, 0.0, 0.0, 1.0],
                [1.0, -2e-06, 1e-06, -0.0, 2e-06, 0.813101, -0.582123, 0.300003, 1e-06, 0.582123, 0.813101, -0.0, 0.0, 0.0, 0.0, 1.0],
                [1.0, -2e-06, 1e-06, -0.0, 2e-06, 0.823292, -0.567618, 0.300002, 1e-06, 0.567618, 0.823292, 0.0, 0.0, 0.0, 0.0, 1.0],
                [1.0, -2e-06, 1e-06, 0.0, 2e-06, 0.812593, -0.582831, 0.300003, 1e-06, 0.582831, 0.812594, 0.0, 0.0, 0.0, 0.0, 1.0],
                [1.0, -2e-06, 1e-06, 0.0, 2e-06, 0.797591, -0.603198, 0.300002, 1e-06, 0.603198, 0.797592, -0.0, 0.0, 0.0, 0.0, 1.0],
                [1.0, -2e-06, 1e-06, 0.0, 2e-06, 0.787426, -0.616408, 0.300003, 1e-06, 0.616408, 0.787427, 0.0, 0.0, 0.0, 0.0, 1.0],
                [1.0, -2e-06, 1e-06, -0.0, 2e-06, 0.790719, -0.61218, 0.300003, 1e-06, 0.61218, 0.790719, -0.0, 0.0, 0.0, 0.0, 1.0],
                [1.0, -2e-06, 1e-06, 0.0, 2e-06, 0.7989, -0.601463, 0.300003, 1e-06, 0.601463, 0.798901, -0.0, 0.0, 0.0, 0.0, 1.0],
                [1.0, -2e-06, 1e-06, 0.0, 2e-06, 0.804464, -0.594001, 0.300003, 1e-06, 0.594001, 0.804464, 0.0, 0.0, 0.0, 0.0, 1.0],
                [1.0, -2e-06, 1e-06, -0.0, 2e-06, 0.811402, -0.584489, 0.300003, 1e-06, 0.584489, 0.811402, 0.0, 0.0, 0.0, 0.0, 1.0],
                [1.0, -2e-06, 1e-06, -0.0, 2e-06, 0.813414, -0.581685, 0.300003, 1e-06, 0.581685, 0.813414, -0.0, 0.0, 0.0, 0.0, 1.0],
                [1.0, -2e-06, 1e-06, -0.0, 2e-06, 0.803825, -0.594866, 0.300003, 1e-06, 0.594866, 0.803825, -0.0, 0.0, 0.0, 0.0, 1.0],
                [1.0, -2e-06, 1e-06, -0.0, 2e-06, 0.790596, -0.612338, 0.300002, 1e-06, 0.612338, 0.790596, -0.0, 0.0, 0.0, 0.0, 1.0],
                [1.0, -2e-06, 1e-06, -0.0, 2e-06, 0.793682, -0.608332, 0.300003, 1e-06, 0.608332, 0.793683, 0.0, 0.0, 0.0, 0.0, 1.0],
                [1.0, -2e-06, 1e-06, -0.0, 2e-06, 0.810998, -0.585049, 0.300003, 1e-06, 0.585049, 0.810998, 0.0, 0.0, 0.0, 0.0, 1.0],
                [1.0, -2e-06, 1e-06, -0.0, 2e-06, 0.822141, -0.569283, 0.300003, 1e-06, 0.569283, 0.822142, -0.0, 0.0, 0.0, 0.0, 1.0],
                [1.0, -2e-06, 1e-06, -0.0, 2e-06, 0.822661, -0.568532, 0.300003, 1e-06, 0.568532, 0.822662, -0.0, 0.0, 0.0, 0.0, 1.0],
                [1.0, -2e-06, 1e-06, -0.0, 2e-06, 0.81894, -0.573879, 0.300003, 1e-06, 0.573879, 0.81894, 0.0, 0.0, 0.0, 0.0, 1.0],
                [1.0, -2e-06, 1e-06, -0.0, 2e-06, 0.822674, -0.568513, 0.300003, 1e-06, 0.568513, 0.822675, -0.0, 0.0, 0.0, 0.0, 1.0],
                [1.0, -2e-06, 1e-06, -0.0, 2e-06, 0.814133, -0.580678, 0.300003, 1e-06, 0.580678, 0.814134, -0.0, 0.0, 0.0, 0.0, 1.0],
                [1.0, -2e-06, 1e-06, -0.0, 2e-06, 0.79543, -0.606045, 0.300003, 1e-06, 0.606045, 0.795431, -0.0, 0.0, 0.0, 0.0, 1.0],
                [1.0, -2e-06, 1e-06, -0.0, 2e-06, 0.783278, -0.621672, 0.300003, 1e-06, 0.621672, 0.783278, 0.0, 0.0, 0.0, 0.0, 1.0],
                [1.0, -2e-06, 1e-06, -0.0, 2e-06, 0.78177, -0.623567, 0.300003, 1e-06, 0.623567, 0.78177, -0.0, 0.0, 0.0, 0.0, 1.0],
                [1.0, -2e-06, 1e-06, 0.0, 2e-06, 0.782129, -0.623117, 0.300002, 1e-06, 0.623117, 0.782129, 0.0, 0.0, 0.0, 0.0, 1.0],
                [1.0, -2e-06, 1e-06, 0.0, 2e-06, 0.776512, -0.630102, 0.300002, 1e-06, 0.630102, 0.776513, 0.0, 0.0, 0.0, 0.0, 1.0],
                [1.0, -2e-06, 1e-06, 0.0, 2e-06, 0.779939, -0.625855, 0.300002, 1e-06, 0.625855, 0.77994, -0.0, 0.0, 0.0, 0.0, 1.0],
                [1.0, -2e-06, 1e-06, -0.0, 2e-06, 0.796434, -0.604725, 0.300003, 1e-06, 0.604725, 0.796434, 0.0, 0.0, 0.0, 0.0, 1.0],
                [1.0, -2e-06, 1e-06, -0.0, 2e-06, 0.801011, -0.59865, 0.300003, 1e-06, 0.59865, 0.801011, -0.0, 0.0, 0.0, 0.0, 1.0]
            ]
        },
        {
            "name": "Tool_R",
            "time": [0.0, 0.0333, 0.0667, 0.1, 0.1333, 0.1667, 0.2, 0.2333, 0.2667, 0.3, 0.3333, 0.3667, 0.4, 0.4333, 0.4667, 0.5, 0.5333, 0.5667, 0.6, 0.6333, 0.6667, 0.7, 0.7333, 0.7667, 0.8, 0.8333, 0.8667, 0.9, 0.9333, 0.9667, 1.0],
            "transform": [
                [1.0, 0.0, 0.0, -0.0, -0.0, -0.99956, -0.029689, 0.271711, 0.0, 0.029689, -0.99956, -0.028915, 0.0, 0.0, 0.0, 1.0],
                [1.0, 0.0, 0.0, -0.0, 0.0, -0.99956, -0.029689, 0.271711, 0.0, 0.029689, -0.99956, -0.028915, 0.0, 0.0, 0.0, 1.0],
                [1.0, -0.0, 0.0, 0.0, 0.0, -0.99956, -0.029689, 0.271711, 0.0, 0.029689, -0.99956, -0.028915, 0.0, 0.0, 0.0, 1.0],
                [1.0, 0.0, 0.0, -0.0, 0.0, -0.99956, -0.029689, 0.271711, 0.0, 0.029689, -0.99956, -0.028915, 0.0, 0.0, 0.0, 1.0],
                [1.0, -0.0, 0.0, -0.0, -0.0, -0.99956, -0.029689, 0.271711, 0.0, 0.029689, -0.99956, -0.028915, 0.0, 0.0, 0.0, 1.0],
                [1.0, 0.0, 0.0, -0.0, -0.0, -0.99956, -0.029689, 0.271711, 0.0, 0.029689, -0.99956, -0.028915, 0.0, 0.0, 0.0, 1.0],
                [1.0, 0.0, 0.0, -0.0, 0.0, -0.99956, -0.029689, 0.271711, 0.0, 0.029689, -0.99956, -0.028915, 0.0, 0.0, 0.0, 1.0],
                [1.0, -0.0, 0.0, 0.0, 0.0, -0.99956, -0.029689, 0.271711, 0.0, 0.029689, -0.99956, -0.028915, 0.0, 0.0, 0.0, 1.0],
                [1.0, 0.0, 0.0, 0.0, -0.0, -0.99956, -0.029689, 0.271711, 0.0, 0.029689, -0.99956, -0.028915, 0.0, 0.0, 0.0, 1.0],
                [1.0, -0.0, 0.0, 0.0, -0.0, -0.99956, -0.029689, 0.271711, 0.0, 0.029689, -0.99956, -0.028915, 0.0, 0.0, 0.0, 1.0],
                [1.0, 0.0, 0.0, -0.0, 0.0, -0.99956, -0.029689, 0.271711, 0.0, 0.029689, -0.99956, -0.028915, 0.0, 0.0, 0.0, 1.0],
                [1.0, 0.0, 0.0, -0.0, -0.0, -0.99956, -0.029689, 0.271711, 0.0, 0.029689, -0.99956, -0.028915, 0.0, 0.0, 0.0, 1.0],
                [1.0, 0.0, 0.0, 0.0, 0.0, -0.99956, -0.029689, 0.271711, 0.0, 0.029689, -0.99956, -0.028915, 0.0, 0.0, 0.0, 1.0],
                [1.0, 0.0, 0.0, 0.0, -0.0, -0.99956, -0.029689, 0.271711, 0.0, 0.029689, -0.99956, -0.028915, 0.0, 0.0, 0.0, 1.0],
                [1.0, 0.0, 0.0, 0.0, 0.0, -0.99956, -0.029689, 0.271711, 0.0, 0.029689, -0.99956, -0.028915, 0.0, 0.0, 0.0, 1.0],
                [1.0, -0.0, 0.0, 0.0, 0.0, -0.99956, -0.029689, 0.271711, 0.0, 0.029689, -0.99956, -0.028915, 0.0, 0.0, 0.0, 1.0],
                [1.0, 0.0, 0.0, -0.0, 0.0, -0.99956, -0.029689, 0.271711, 0.0, 0.029689, -0.99956, -0.028915, 0.0, 0.0, 0.0, 1.0],
                [1.0, 0.0, 0.0, 0.0, -0.0, -0.99956, -0.029689, 0.271711, 0.0, 0.029689, -0.99956, -0.028915, 0.0, 0.0, 0.0, 1.0],
                [1.0, 0.0, 0.0, -0.0, -0.0, -0.99956, -0.029689, 0.271711, 0.0, 0.029689, -0.99956, -0.028915, 0.0, 0.0, 0.0, 1.0],
                [1.0, 0.0, 0.0, -0.0, 0.0, -0.99956, -0.029689, 0.271711, 0.0, 0.029689, -0.99956, -0.028915, 0.0, 0.0, 0.0, 1.0],
                [1.0, -0.0, 0.0, 0.0, 0.0, -0.99956, -0.029689, 0.271711, 0.0, 0.029689, -0.99956, -0.028915, 0.0, 0.0, 0.0, 1.0],
                [1.0, 0.0, 0.0, 0.0, -0.0, -0.99956, -0.029689, 0.271711, 0.0, 0.029689, -0.99956, -0.028915, 0.0, 0.0, 0.0, 1.0],
                [1.0, 0.0, 0.0, 0.0, 0.0, -0.99956, -0.029689, 0.271711, 0.0, 0.029689, -0.99956, -0.028915, 0.0, 0.0, 0.0, 1.0],
                [1.0, -0.0, 0.0, 0.0, -0.0, -0.99956, -0.029689, 0.271711, 0.0, 0.029689, -0.99956, -0.028915, 0.0, 0.0, 0.0, 1.0],
                [1.0, -0.0, 0.0, 0.0, -0.0, -0.99956, -0.029689, 0.271711, 0.0, 0.029689, -0.99956, -0.028915, 0.0, 0.0, 0.0, 1.0],
                [1.0, -0.0, 0.0, -0.0, 0.0, -0.999559, -0.029689, 0.271711, 0.0, 0.029689, -0.99956, -0.028915, 0.0, 0.0, 0.0, 1.0],
                [1.0, 0.0, 0.0, -0.0, -0.0, -0.99956, -0.029689, 0.271711, 0.0, 0.029689, -0.99956, -0.028915, 0.0, 0.0, 0.0, 1.0],
                [1.0, -0.0, 0.0, -0.0, -0.0, -0.99956, -0.029689, 0.271711, 0.0, 0.029689, -0.99956, -0.028915, 0.0, 0.0, 0.0, 1.0],
                [1.0, -0.0, 0.0, 0.0, -0.0, -0.99956, -0.029689, 0.271711, 0.0, 0.029689, -0.99956, -0.028915, 0.0, 0.0, 0.0, 1.0],
                [1.0, -0.0, 0.0, 0.0, -0.0, -0.99956, -0.029689, 0.271711, 0.0, 0.029689, -0.99956, -0.028915, 0.0, 0.0, 0.0, 1.0],
                [1.0, -0.0, 0.0, -0.0, -0.0, -0.99956, -0.029689, 0.271711, 0.0, 0.029689, -0.99956, -0.028915, 0.0, 0.0, 0.0, 1.0]
            ]
        },
        {
            "name": "Elbow_R",
            "time": [0.0, 1.0],
            "transform": [
                [-1.0, 0.0, -0.0, -0.0, -0.0, 0.003946, -0.999992, 0.360002, -0.0, -0.999992, -0.003946, -0.001016, 0.0, 0.0, 0.0, 1.0],
                [-1.0, 0.0, -0.0, -0.0, 0.0, 0.003946, -0.999992, 0.359343, -0.0, -0.999992, -0.003946, -0.001018, 0.0, 0.0, 0.0, 1.0]
            ]
        },
        {
            "name": "Shoulder_L",
            "time": [0.0, 0.0333, 0.0667, 0.1, 0.1333, 0.1667, 0.2, 0.2333, 0.2667, 0.3, 0.3333, 0.3667, 0.4, 0.4333, 0.4667, 0.5, 0.5333, 0.5667, 0.6, 0.6333, 0.6667, 0.7, 0.7333, 0.7667, 0.8, 0.8333, 0.8667, 0.9, 0.9333, 0.9667, 1.0],
            "transform": [
                [0.0, -0.952114, -0.305743, -0.0, 0.0, -0.305743, 0.952114, 0.4, -1.0, -0.0, 0.0, 0.0, 0.0, 0.0, 0.0, 1.0],
                [0.0, -0.952114, -0.305743, -0.0, 0.0, -0.305743, 0.952114, 0.4, -1.0, -0.0, 0.0, 0.0, 0.0, 0.0, 0.0, 1.0],
                [0.0, -0.952114, -0.305743, -0.0, 0.0, -0.305743, 0.952114, 0.4, -1.0, -0.0, 0.0, 0.0, 0.0, 0.0, 0.0, 1.0],
                [0.0, -0.952114, -0.305743, -0.0, 0.0, -0.305743, 0.952114, 0.4, -1.0, -0.0, 0.0, 0.0, 0.0, 0.0, 0.0, 1.0],
                [0.0, -0.952114, -0.305743, -0.0, 0.0, -0.305743, 0.952114, 0.4, -1.0, -0.0, 0.0, 0.0, 0.0, 0.0, 0.0, 1.0],
                [0.0, -0.952114, -0.305743, -0.0, 0.0, -0.305743, 0.952114, 0.4, -1.0, -0.0, 0.0, 0.0, 0.0, 0.0, 0.0, 1.0],
                [0.0, -0.952114, -0.305743, -0.0, 0.0, -0.305743, 0.952114, 0.4, -1.0, -0.0, 0.0, 0.0, 0.0, 0.0, 0.0, 1.0],
                [0.0, -0.952114, -0.305743, -0.0, 0.0, -0.305743, 0.952114, 0.4, -1.0, -0.0, 0.0, 0.0, 0.0, 0.0, 0.0, 1.0],
                [0.0, -0.952114, -0.305743, -0.0, 0.0, -0.305743, 0.952114, 0.4, -1.0, -0.0, 0.0, 0.0, 0.0, 0.0, 0.0, 1.0],
                [0.0, -0.952114, -0.305743, -0.0, 0.0, -0.305743, 0.952114, 0.4, -1.0, -0.0, 0.0, 0.0, 0.0, 0.0, 0.0, 1.0],
                [0.0, -0.952114, -0.305743, -0.0, 0.0, -0.305743, 0.952114, 0.4, -1.0, -0.0, 0.0, 0.0, 0.0, 0.0, 0.0, 1.0],
                [0.0, -0.952114, -0.305743, -0.0, 0.0, -0.305743, 0.952114, 0.4, -1.0, -0.0, 0.0, 0.0, 0.0, 0.0, 0.0, 1.0],
                [0.0, -0.952114, -0.305743, -0.0, 0.0, -0.305743, 0.952114, 0.4, -1.0, -0.0, 0.0, 0.0, 0.0, 0.0, 0.0, 1.0],
                [0.0, -0.952114, -0.305743, -0.0, 0.0, -0.305743, 0.952114, 0.4, -1.0, -0.0, 0.0, 0.0, 0.0, 0.0, 0.0, 1.0],
                [0.0, -0.952114, -0.305743, -0.0, 0.0, -0.305743, 0.952114, 0.4, -1.0, -0.0, 0.0, 0.0, 0.0, 0.0, 0.0, 1.0],
                [0.0, -0.952114, -0.305743, -0.0, 0.0, -0.305743, 0.952114, 0.4, -1.0, -0.0, 0.0, 0.0, 0.0, 0.0, 0.0, 1.0],
                [0.0, -0.952114, -0.305743, -0.0, 0.0, -0.305743, 0.952114, 0.4, -1.0, -0.0, 0.0, 0.0, 0.0, 0.0, 0.0, 1.0],
                [0.0, -0.952114, -0.305743, -0.0, 0.0, -0.305743, 0.952114, 0.4, -1.0, -0.0, 0.0, 0.0, 0.0, 0.0, 0.0, 1.0],
                [0.0, -0.952114, -0.305743, -0.0, 0.0, -0.305743, 0.952114, 0.4, -1.0, -0.0, 0.0, 0.0, 0.0, 0.0, 0.0, 1.0],
                [0.0, -0.952114, -0.305743, -0.0, 0.0, -0.305743, 0.952114, 0.4, -1.0, -0.0, 0.0, 0.0, 0.0, 0.0, 0.0, 1.0],
                [0.0, -0.952114, -0.305743, -0.0, 0.0, -0.305743, 0.952114, 0.4, -1.0, -0.0, 0.0, 0.0, 0.0, 0.0, 0.0, 1.0],
                [0.0, -0.952114, -0.305743, -0.0, 0.0, -0.305743, 0.952114, 0.4, -1.0, -0.0, 0.0, 0.0, 0.0, 0.0, 0.0, 1.0],
                [0.0, -0.952114, -0.305743, -0.0, 0.0, -0.305743, 0.952114, 0.4, -1.0, -0.0, 0.0, 0.0, 0.0, 0.0, 0.0, 1.0],
                [0.0, -0.952114, -0.305743, -0.0, 0.0, -0.305743, 0.952114, 0.4, -1.0, -0.0, 0.0, 0.0, 0.0, 0.0, 0.0, 1.0],
                [0.0, -0.952114, -0.305743, -0.0, 0.0, -0.305743, 0.952114, 0.4, -1.0, -0.0, 0.0, 0.0, 0.0, 0.0, 0.0, 1.0],
                [0.0, -0.952114, -0.305743, -0.0, 0.0, -0.305743, 0.952114, 0.4, -1.0, -0.0, 0.0, 0.0, 0.0, 0.0, 0.0, 1.0],
                [0.0, -0.952114, -0.305743, -0.0, 0.0, -0.305743, 0.952114, 0.4, -1.0, -0.0, 0.0, 0.0, 0.0, 0.0, 0.0, 1.0],
                [0.0, -0.952114, -0.305743, -0.0, 0.0, -0.305743, 0.952114, 0.4, -1.0, -0.0, 0.0, 0.0, 0.0, 0.0, 0.0, 1.0],
                [0.0, -0.952114, -0.305743, -0.0, 0.0, -0.305743, 0.952114, 0.4, -1.0, -0.0, 0.0, 0.0, 0.0, 0.0, 0.0, 1.0],
                [0.0, -0.952114, -0.305743, -0.0, 0.0, -0.305743, 0.952114, 0.4, -1.0, -0.0, 0.0, 0.0, 0.0, 0.0, 0.0, 1.0],
                [0.0, -0.952114, -0.305743, -0.0, 0.0, -0.305743, 0.952114, 0.4, -1.0, -0.0, 0.0, 0.0, 0.0, 0.0, 0.0, 1.0]
            ]
        },
        {
            "name": "Arm_L",
            "time": [0.0, 0.0333, 0.0667, 0.1, 0.1333, 0.1667, 0.2, 0.2333, 0.2667, 0.3, 0.3333, 0.3667, 0.4, 0.4333, 0.4667, 0.5, 0.5333, 0.5667, 0.6, 0.6333, 0.6667, 0.7, 0.7333, 0.7667, 0.8, 0.8333, 0.8667, 0.9, 0.9333, 0.9667, 1.0],
            "transform": [
                [0.623059, 0.256886, 0.738788, 0.0, -0.716687, 0.565827, 0.407674, 0.39386, -0.3133, -0.783485, 0.536651, -0.0, 0.0, 0.0, 0.0, 1.0],
                [0.626335, 0.26446, 0.733324, 0.0, -0.71083, 0.579945, 0.397975, 0.39386, -0.320039, -0.770535, 0.551227, -0.0, 0.0, 0.0, 0.0, 1.0],
                [0.625933, 0.261, 0.734905, 0.0, -0.711557, 0.576833, 0.401185, 0.39386, -0.319208, -0.774042, 0.546776, -0.0, 0.0, 0.0, 0.0, 1.0],
                [0.62329, 0.255703, 0.739003, 0.0, -0.716279, 0.565874, 0.408325, 0.39386, -0.313773, -0.783838, 0.535858, -0.0, 0.0, 0.0, 0.0, 1.0],
                [0.619615, 0.249821, 0.744088, 0.0, -0.72267, 0.55153, 0.416608, 0.39386, -0.306309, -0.795866, 0.522275, -0.0, 0.0, 0.0, 0.0, 1.0],
                [0.618601, 0.245902, 0.746234, 0.0, -0.724399, 0.546297, 0.420482, 0.39386, -0.304268, -0.800681, 0.516072, -0.0, 0.0, 0.0, 0.0, 1.0],
                [0.621261, 0.25018, 0.742593, 0.0, -0.719832, 0.556674, 0.414675, 0.39386, -0.309639, -0.792163, 0.525928, -0.0, 0.0, 0.0, 0.0, 1.0],
                [0.623477, 0.258027, 0.738037, 0.0, -0.715948, 0.567724, 0.406334, 0.39386, -0.314156, -0.781736, 0.538697, -0.0, 0.0, 0.0, 0.0, 1.0],
                [0.623506, 0.256445, 0.738563, 0.0, -0.715897, 0.566939, 0.407517, 0.39386, -0.314215, -0.782825, 0.537079, -0.0, 0.0, 0.0, 0.0, 1.0],
                [0.622038, 0.249453, 0.742187, 0.0, -0.718479, 0.558613, 0.414415, 0.39386, -0.311218, -0.791027, 0.526705, -0.0, 0.0, 0.0, 0.0, 1.0],
                [0.621689, 0.248194, 0.742901, 0.0, -0.719088, 0.556854, 0.415722, 0.39386, -0.310508, -0.792661, 0.524664, -0.0, 0.0, 0.0, 0.0, 1.0],
                [0.620728, 0.249157, 0.743382, 0.0, -0.720754, 0.554499, 0.415984, 0.39386, -0.30856, -0.794009, 0.523775, -0.0, 0.0, 0.0, 0.0, 1.0],
                [0.620315, 0.249226, 0.743704, 0.0, -0.721467, 0.553296, 0.41635, 0.39386, -0.307723, -0.794826, 0.523027, -0.0, 0.0, 0.0, 0.0, 1.0],
                [0.62124, 0.251609, 0.742128, 0.0, -0.719869, 0.557407, 0.413624, 0.39386, -0.309596, -0.791195, 0.52741, -0.0, 0.0, 0.0, 0.0, 1.0],
                [0.623083, 0.256835, 0.738784, 0.0, -0.716644, 0.565874, 0.407686, 0.39386, -0.313351, -0.783467, 0.536646, -0.0, 0.0, 0.0, 0.0, 1.0],
                [0.623115, 0.257248, 0.738614, 0.0, -0.716589, 0.566196, 0.407335, 0.39386, -0.313414, -0.783099, 0.537147, -0.0, 0.0, 0.0, 0.0, 1.0],
                [0.621119, 0.252051, 0.742079, 0.0, -0.720078, 0.557291, 0.413417, 0.39386, -0.309351, -0.791136, 0.527641, -0.0, 0.0, 0.0, 0.0, 1.0],
                [0.619736, 0.248844, 0.744314, 0.0, -0.722462, 0.551346, 0.417212, 0.39386, -0.306554, -0.7963, 0.52147, -0.0, 0.0, 0.0, 0.0, 1.0],
                [0.619647, 0.250882, 0.743704, 0.0, -0.722616, 0.552218, 0.415789, 0.39386, -0.306373, -0.795055, 0.523472, -0.0, 0.0, 0.0, 0.0, 1.0],
                [0.620193, 0.254401, 0.742051, 0.0, -0.721677, 0.555818, 0.412611, 0.39386, -0.307477, -0.79142, 0.528311, -0.0, 0.0, 0.0, 0.0, 1.0],
                [0.619841, 0.255799, 0.741865, 0.0, -0.722282, 0.555541, 0.411926, 0.39386, -0.306766, -0.791164, 0.529106, -0.0, 0.0, 0.0, 0.0, 1.0],
                [0.620239, 0.255949, 0.74148, 0.0, -0.721598, 0.556815, 0.411402, 0.39386, -0.30757, -0.790219, 0.530052, -0.0, 0.0, 0.0, 0.0, 1.0],
                [0.62175, 0.256769, 0.73993, 0.0, -0.718982, 0.561808, 0.409189, 0.39386, -0.310632, -0.78641, 0.533916, -0.0, 0.0, 0.0, 0.0, 1.0],
                [0.62296, 0.254211, 0.739795, 0.0, -0.716861, 0.56405, 0.409826, 0.39386, -0.313099, -0.785636, 0.533615, -0.0, 0.0, 0.0, 0.0, 1.0],
                [0.623228, 0.24917, 0.741283, 0.0, -0.716389, 0.56206, 0.41337, 0.39386, -0.313646, -0.788671, 0.528795, -0.0, 0.0, 0.0, 0.0, 1.0],
                [0.623441, 0.245718, 0.742256, 0.0, -0.716012, 0.560778, 0.415756, 0.39386, -0.314082, -0.790664, 0.52555, -0.0, 0.0, 0.0, 0.0, 1.0],
                [0.623863, 0.245672, 0.741917, 0.0, -0.715265, 0.562036, 0.415344, 0.39386, -0.314946, -0.789785, 0.526354, -0.0, 0.0, 0.0, 0.0, 1.0],
                [0.623173, 0.246277, 0.742296, 0.0, -0.716486, 0.560275, 0.415618, 0.39386, -0.313533, -0.790846, 0.525603, -0.0, 0.0, 0.0, 0.0, 1.0],
                [0.62109, 0.243593, 0.744922, 0.0, -0.720129, 0.552464, 0.419759, 0.39386, -0.309292, -0.797148, 0.518549, -0.0, 0.0, 0.0, 0.0, 1.0],
                [0.620956, 0.241898, 0.745586, 0.0, -0.72036, 0.551104, 0.421146, 0.39386, -0.309021, -0.798604, 0.516466, -0.0, 0.0, 0.0, 0.0, 1.0],
                [0.623097, 0.243008, 0.743436, 0.0, -0.71662, 0.55821, 0.418158, 0.39386, -0.313378, -0.793314, 0.521964, -0.0, 0.0, 0.0, 0.0, 1.0]
            ]
        },
        {
            "name": "Hand_L",
            "time": [0.0, 0.0333, 0.0667, 0.1, 0.1333, 0.1667, 0.2, 0.2333, 0.2667, 0.3, 0.3333, 0.3667, 0.4, 0.4333, 0.4667, 0.5, 0.5333, 0.5667, 0.6, 0.6333, 0.6667, 0.7, 0.7333, 0.7667, 0.8, 0.8333, 0.8667, 0.9, 0.9333, 0.9667, 1.0],
            "transform": [
                [1.0, -0.0, 0.0, -0.0, 0.0, 0.778892, -0.627159, 0.300003, 0.0, 0.627159, 0.778891, 0.0, 0.0, 0.0, 0.0, 1.0],
                [1.0, -0.0, -0.0, -0.0, 0.0, 0.803639, -0.595118, 0.300002, 0.0, 0.595118, 0.803638, 0.0, 0.0, 0.0, 0.0, 1.0],
                [1.0, -0.0, 0.0, -0.0, 0.0, 0.794428, -0.607359, 0.300002, 0.0, 0.607359, 0.794427, 0.0, 0.0, 0.0, 0.0, 1.0],
                [1.0, -0.0, 0.0, 0.0, 0.0, 0.776197, -0.63049, 0.300003, 0.0, 0.63049, 0.776197, 0.0, 0.0, 0.0, 0.0, 1.0],
                [1.0, -0.0, 0.0, -0.0, 0.0, 0.753434, -0.657524, 0.300002, 0.0, 0.657524, 0.753433, -0.0, 0.0, 0.0, 0.0, 1.0],
                [1.0, -0.0, 0.0, -0.0, 0.0, 0.740265, -0.672316, 0.300002, 0.0, 0.672316, 0.740264, -0.0, 0.0, 0.0, 0.0, 1.0],
                [1.0, -0.0, 0.0, 0.0, 0.0, 0.757501, -0.652834, 0.300002, 0.0, 0.652834, 0.757501, -0.0, 0.0, 0.0, 0.0, 1.0],
                [1.0, -0.0, 0.0, -0.0, 0.0, 0.782602, -0.622523, 0.300002, 0.0, 0.622523, 0.782601, -0.0, 0.0, 0.0, 0.0, 1.0],
                [1.0, -0.0, 0.0, 0.0, 0.0, 0.778536, -0.6276, 0.300003, 0.0, 0.6276, 0.778536, 0.0, 0.0, 0.0, 0.0, 1.0],
                [1.0, -0.0, 0.0, -0.0, 0.0, 0.756919, -0.653509, 0.300002, 0.0, 0.653509, 0.756918, 0.0, 0.0, 0.0, 0.0, 1.0],
                [1.0, -0.0, 0.0, 0.0, 0.0, 0.752719, -0.658342, 0.300003, 0.0, 0.658342, 0.752719, 0.0, 0.0, 0.0, 0.0, 1.0],
                [1.0, -0.0, 0.0, -0.0, 0.0, 0.753637, -0.657291, 0.300003, 0.0, 0.657291, 0.753637, 0.0, 0.0, 0.0, 0.0, 1.0],
                [1.0, -0.0, 0.0, 0.0, 0.0, 0.75306, -0.657952, 0.300002, 0.0, 0.657952, 0.75306, 0.0, 0.0, 0.0, 0.0, 1.0],
                [1.0, -0.0, 0.0, 0.0, 0.0, 0.761426, -0.648252, 0.300003, 0.0, 0.648252, 0.761426, 0.0, 0.0, 0.0, 0.0, 1.0],
                [1.0, -0.0, 0.0, 0.0, 0.0, 0.778803, -0.627269, 0.300003, 0.0, 0.627268, 0.778803, 0.0, 0.0, 0.0, 0.0, 1.0],
                [1.0, -0.0, 0.0, 0.0, 0.0, 0.779937, -0.625859, 0.300003, 0.0, 0.625858, 0.779936, -0.0, 0.0, 0.0, 0.0, 1.0],
                [1.0, -0.0, 0.0, -0.0, 0.0, 0.76242, -0.647083, 0.300002, 0.0, 0.647083, 0.76242, 0.0, 0.0, 0.0, 0.0, 1.0],
                [1.0, -0.0, -0.0, 0.0, 0.0, 0.750895, -0.660422, 0.300003, 0.0, 0.660422, 0.750894, 0.0, 0.0, 0.0, 0.0, 1.0],
                [1.0, -0.0, 0.0, -0.0, 0.0, 0.756469, -0.65403, 0.300003, 0.0, 0.654029, 0.756469, 0.0, 0.0, 0.0, 0.0, 1.0],
                [1.0, -0.0, 0.0, -0.0, 0.0, 0.76714, -0.641481, 0.300003, 0.0, 0.641481, 0.767139, 0.0, 0.0, 0.0, 0.0, 1.0],
                [1.0, -0.0, 0.0, -0.0, 0.0, 0.770267, -0.637722, 0.300002, 0.0, 0.637722, 0.770267, 0.0, 0.0, 0.0, 0.0, 1.0],
                [1.0, -0.0, 0.0, -0.0, 0.0, 0.771381, -0.636374, 0.300003, 0.0, 0.636374, 0.77138, -0.0, 0.0, 0.0, 0.0, 1.0],
                [1.0, -0.0, 0.0, 0.0, 0.0, 0.776249, -0.630426, 0.300002, 0.0, 0.630426, 0.776249, -0.0, 0.0, 0.0, 0.0, 1.0],
                [1.0, -0.0, 0.0, -0.0, 0.0, 0.771638, -0.636062, 0.300003, 0.0, 0.636062, 0.771638, -0.0, 0.0, 0.0, 0.0, 1.0],
                [1.0, -0.0, 0.0, 0.0, 0.0, 0.758361, -0.651836, 0.300003, 0.0, 0.651835, 0.758361, 0.0, 0.0, 0.0, 0.0, 1.0],
                [1.0, -0.0, 0.0, -0.0, 0.0, 0.748995, -0.662576, 0.300002, -0.0, 0.662576, 0.748994, -0.0, 0.0, 0.0, 0.0, 1.0],
                [1.0, -0.0, 0.0, -0.0, 0.0, 0.749673, -0.661809, 0.300003, 0.0, 0.661809, 0.749673, 0.0, 0.0, 0.0, 0.0, 1.0],
                [1.0, -0.0, 0.0, -0.0, 0.0, 0.750082, -0.661346, 0.300002, 0.0, 0.661345, 0.750081, 0.0, 0.0, 0.0, 0.0, 1.0],
                [1.0, -0.0, 0.0, -0.0, 0.0, 0.738262, -0.674515, 0.300002, 0.0, 0.674514, 0.738261, -0.0, 0.0, 0.0, 0.0, 1.0],
                [1.0, -0.0, 0.0, 0.0, 0.0, 0.732949, -0.680284, 0.300003, 0.0, 0.680284, 0.732948, 0.0, 0.0, 0.0, 0.0, 1.0],
                [1.0, -0.0, 0.0, 0.0, 0.0, 0.740448, -0.672115, 0.300003, 0.0, 0.672114, 0.740447, 0.0, 0.0, 0.0, 0.0, 1.0]
            ]
        },
        {
            "name": "Tool_L",
            "time": [0.0, 0.0333, 0.0667, 0.1, 0.1333, 0.1667, 0.2, 0.2333, 0.2667, 0.3, 0.3333, 0.3667, 0.4, 0.4333, 0.4667, 0.5, 0.5333, 0.5667, 0.6, 0.6333, 0.6667, 0.7, 0.7333, 0.7667, 0.8, 0.8333, 0.8667, 0.9, 0.9333, 0.9667, 1.0],
            "transform": [
                [1.0, 0.0, 0.0, 0.0, 0.0, -0.99956, -0.029689, 0.271711, 0.0, 0.029689, -0.99956, -0.028915, 0.0, 0.0, 0.0, 1.0],
                [1.0, 0.0, 0.0, -0.0, -0.0, -0.99956, -0.029689, 0.271711, 0.0, 0.029689, -0.99956, -0.028915, 0.0, 0.0, 0.0, 1.0],
                [1.0, 0.0, 0.0, 0.0, -0.0, -0.99956, -0.029689, 0.271711, 0.0, 0.029689, -0.99956, -0.028915, 0.0, 0.0, 0.0, 1.0],
                [1.0, 0.0, 0.0, -0.0, 0.0, -0.99956, -0.029689, 0.271711, 0.0, 0.029689, -0.99956, -0.028915, 0.0, 0.0, 0.0, 1.0],
                [1.0, -0.0, 0.0, 0.0, 0.0, -0.99956, -0.029689, 0.271711, 0.0, 0.029689, -0.99956, -0.028915, 0.0, 0.0, 0.0, 1.0],
                [1.0, 0.0, 0.0, -0.0, -0.0, -0.99956, -0.029689, 0.271711, 0.0, 0.029689, -0.99956, -0.028915, 0.0, 0.0, 0.0, 1.0],
                [1.0, 0.0, 0.0, 0.0, 0.0, -0.99956, -0.029689, 0.271711, 0.0, 0.029689, -0.99956, -0.028915, 0.0, 0.0, 0.0, 1.0],
                [1.0, 0.0, 0.0, 0.0, -0.0, -0.99956, -0.029689, 0.271711, 0.0, 0.029689, -0.99956, -0.028915, 0.0, 0.0, 0.0, 1.0],
                [1.0, 0.0, 0.0, -0.0, -0.0, -0.99956, -0.029689, 0.271711, 0.0, 0.029689, -0.99956, -0.028915, 0.0, 0.0, 0.0, 1.0],
                [1.0, 0.0, 0.0, -0.0, -0.0, -0.99956, -0.029689, 0.271711, 0.0, 0.029689, -0.99956, -0.028915, 0.0, 0.0, 0.0, 1.0],
                [1.0, 0.0, 0.0, -0.0, -0.0, -0.99956, -0.029689, 0.271711, 0.0, 0.029689, -0.99956, -0.028915, 0.0, 0.0, 0.0, 1.0],
                [1.0, 0.0, 0.0, 0.0, 0.0, -0.99956, -0.029689, 0.271711, 0.0, 0.029689, -0.99956, -0.028915, 0.0, 0.0, 0.0, 1.0],
                [1.0, 0.0, 0.0, 0.0, 0.0, -0.99956, -0.029689, 0.271711, 0.0, 0.029689, -0.99956, -0.028915, 0.0, 0.0, 0.0, 1.0],
                [1.0, -0.0, 0.0, 0.0, -0.0, -0.99956, -0.029689, 0.271711, 0.0, 0.029689, -0.99956, -0.028915, 0.0, 0.0, 0.0, 1.0],
                [1.0, 0.0, 0.0, 0.0, 0.0, -0.99956, -0.029689, 0.271711, 0.0, 0.029689, -0.99956, -0.028915, 0.0, 0.0, 0.0, 1.0],
                [1.0, -0.0, 0.0, 0.0, -0.0, -0.99956, -0.029689, 0.271711, 0.0, 0.029689, -0.99956, -0.028915, 0.0, 0.0, 0.0, 1.0],
                [1.0, -0.0, 0.0, 0.0, -0.0, -0.99956, -0.029689, 0.271711, 0.0, 0.029689, -0.99956, -0.028915, 0.0, 0.0, 0.0, 1.0],
                [1.0, -0.0, 0.0, 0.0, -0.0, -0.99956, -0.029689, 0.271711, 0.0, 0.029689, -0.99956, -0.028915, 0.0, 0.0, 0.0, 1.0],
                [1.0, 0.0, 0.0, 0.0, -0.0, -0.99956, -0.029689, 0.271711, 0.0, 0.029689, -0.99956, -0.028915, 0.0, 0.0, 0.0, 1.0],
                [1.0, -0.0, 0.0, 0.0, 0.0, -0.99956, -0.029689, 0.271711, 0.0, 0.029689, -0.99956, -0.028915, 0.0, 0.0, 0.0, 1.0],
                [1.0, -0.0, 0.0, -0.0, -0.0, -0.99956, -0.029689, 0.271711, 0.0, 0.029689, -0.99956, -0.028915, 0.0, 0.0, 0.0, 1.0],
                [1.0, 0.0, 0.0, 0.0, -0.0, -0.99956, -0.029689, 0.271711, 0.0, 0.029689, -0.99956, -0.028915, 0.0, 0.0, 0.0, 1.0],
                [1.0, 0.0, 0.0, 0.0, -0.0, -0.99956, -0.029689, 0.271711, 0.0, 0.029689, -0.99956, -0.028915, 0.0, 0.0, 0.0, 1.0],
                [1.0, 0.0, 0.0, 0.0, 0.0, -0.99956, -0.029689, 0.271711, 0.0, 0.029689, -0.99956, -0.028915, 0.0, 0.0, 0.0, 1.0],
                [1.0, -0.0, 0.0, 0.0, -0.0, -0.99956, -0.029689, 0.271711, 0.0, 0.029689, -0.99956, -0.028915, 0.0, 0.0, 0.0, 1.0],
                [1.0, -0.0, 0.0, 0.0, -0.0, -0.99956, -0.029689, 0.271711, 0.0, 0.029689, -0.99956, -0.028915, 0.0, 0.0, 0.0, 1.0],
                [1.0, 0.0, 0.0, 0.0, 0.0, -0.99956, -0.029689, 0.271711, 0.0, 0.029689, -0.99956, -0.028915, 0.0, 0.0, 0.0, 1.0],
                [1.0, 0.0, 0.0, -0.0, -0.0, -0.99956, -0.029689, 0.271711, 0.0, 0.029689, -0.99956, -0.028915, 0.0, 0.0, 0.0, 1.0],
                [1.0, 0.0, 0.0, -0.0, -0.0, -0.99956, -0.029689, 0.271711, 0.0, 0.029689, -0.99956, -0.028915, 0.0, 0.0, 0.0, 1.0],
                [1.0, 0.0, 0.0, 0.0, 0.0, -0.99956, -0.029689, 0.271711, 0.0, 0.029689, -0.99956, -0.028915, 0.0, 0.0, 0.0, 1.0],
                [1.0, 0.0, 0.0, -0.0, -0.0, -0.99956, -0.029689, 0.271711, 0.0, 0.029689, -0.99956, -0.028915, 0.0, 0.0, 0.0, 1.0]
            ]
        },
        {
            "name": "Elbow_L",
            "time": [0.0, 1.0],
            "transform": [
                [-1.0, 0.0, -0.0, 0.0, 0.0, 0.003946, -0.999992, 0.362724, -0.0, -0.999993, -0.003946, -0.001005, 0.0, 0.0, 0.0, 1.0],
                [-1.0, 0.0, -0.0, 0.0, 0.0, 0.003946, -0.999992, 0.368268, -0.0, -0.999993, -0.003946, -0.000983, 0.0, 0.0, 0.0, 1.0]
            ]
        },
        {
            "name": "IK-Thigh_R",
            "time": [0.0, 0.0333, 0.0667, 0.1, 0.1333, 0.1667, 0.2, 0.2333, 0.2667, 0.3, 0.3333, 0.3667, 0.4, 0.4333, 0.4667, 0.5, 0.5333, 0.5667, 0.6, 0.6333, 0.6667, 0.7, 0.7333, 0.7667, 0.8, 0.8333, 0.8667, 0.9, 0.9333, 0.9667, 1.0],
            "transform": [
                [1.0, -0.0, -0.0, 0.124994, -0.0, -0.999984, 0.005946, -0.002831, -0.0, -0.005946, -0.999982, -1.2e-05, 0.0, 0.0, 0.0, 1.0],
                [1.0, -0.0, -0.0, 0.124994, -0.0, -0.999984, 0.005946, -0.002831, -0.0, -0.005946, -0.999982, -1.2e-05, 0.0, 0.0, 0.0, 1.0],
                [1.0, -0.0, -0.0, 0.124994, -0.0, -0.999984, 0.005946, -0.002831, -0.0, -0.005946, -0.999982, -1.2e-05, 0.0, 0.0, 0.0, 1.0],
                [1.0, -0.0, -0.0, 0.124994, -0.0, -0.999984, 0.005946, -0.002831, -0.0, -0.005946, -0.999982, -1.2e-05, 0.0, 0.0, 0.0, 1.0],
                [1.0, -0.0, -0.0, 0.124994, -0.0, -0.999984, 0.005946, -0.002831, -0.0, -0.005946, -0.999982, -1.2e-05, 0.0, 0.0, 0.0, 1.0],
                [1.0, -0.0, -0.0, 0.124994, -0.0, -0.999984, 0.005946, -0.002831, -0.0, -0.005946, -0.999982, -1.2e-05, 0.0, 0.0, 0.0, 1.0],
                [1.0, -0.0, -0.0, 0.124994, -0.0, -0.999984, 0.005946, -0.002831, -0.0, -0.005946, -0.999982, -1.2e-05, 0.0, 0.0, 0.0, 1.0],
                [1.0, -0.0, -0.0, 0.124994, -0.0, -0.999984, 0.005946, -0.002831, -0.0, -0.005946, -0.999982, -1.2e-05, 0.0, 0.0, 0.0, 1.0],
                [1.0, -0.0, -0.0, 0.124994, -0.0, -0.999984, 0.005946, -0.002831, -0.0, -0.005946, -0.999982, -1.2e-05, 0.0, 0.0, 0.0, 1.0],
                [1.0, -0.0, -0.0, 0.124994, -0.0, -0.999984, 0.005946, -0.002831, -0.0, -0.005946, -0.999982, -1.2e-05, 0.0, 0.0, 0.0, 1.0],
                [1.0, -0.0, -0.0, 0.124994, -0.0, -0.999984, 0.005946, -0.002831, -0.0, -0.005946, -0.999982, -1.2e-05, 0.0, 0.0, 0.0, 1.0],
                [1.0, -0.0, -0.0, 0.124994, -0.0, -0.999984, 0.005946, -0.002831, -0.0, -0.005946, -0.999982, -1.2e-05, 0.0, 0.0, 0.0, 1.0],
                [1.0, -0.0, -0.0, 0.124994, -0.0, -0.999984, 0.005946, -0.002831, -0.0, -0.005946, -0.999982, -1.2e-05, 0.0, 0.0, 0.0, 1.0],
                [1.0, -0.0, -0.0, 0.124994, -0.0, -0.999984, 0.005946, -0.002831, -0.0, -0.005946, -0.999982, -1.2e-05, 0.0, 0.0, 0.0, 1.0],
                [1.0, -0.0, -0.0, 0.124994, -0.0, -0.999984, 0.005946, -0.002831, -0.0, -0.005946, -0.999982, -1.2e-05, 0.0, 0.0, 0.0, 1.0],
                [1.0, -0.0, -0.0, 0.124994, -0.0, -0.999984, 0.005946, -0.002831, -0.0, -0.005946, -0.999982, -1.2e-05, 0.0, 0.0, 0.0, 1.0],
                [1.0, -0.0, -0.0, 0.124994, -0.0, -0.999984, 0.005946, -0.002831, -0.0, -0.005946, -0.999982, -1.2e-05, 0.0, 0.0, 0.0, 1.0],
                [1.0, -0.0, -0.0, 0.124994, -0.0, -0.999984, 0.005946, -0.002831, -0.0, -0.005946, -0.999982, -1.2e-05, 0.0, 0.0, 0.0, 1.0],
                [1.0, -0.0, -0.0, 0.124994, -0.0, -0.999984, 0.005946, -0.002831, -0.0, -0.005946, -0.999982, -1.2e-05, 0.0, 0.0, 0.0, 1.0],
                [1.0, -0.0, -0.0, 0.124994, -0.0, -0.999984, 0.005946, -0.002831, -0.0, -0.005946, -0.999982, -1.2e-05, 0.0, 0.0, 0.0, 1.0],
                [1.0, -0.0, -0.0, 0.124994, -0.0, -0.999984, 0.005946, -0.002831, -0.0, -0.005946, -0.999982, -1.2e-05, 0.0, 0.0, 0.0, 1.0],
                [1.0, -0.0, -0.0, 0.124994, -0.0, -0.999984, 0.005946, -0.002831, -0.0, -0.005946, -0.999982, -1.2e-05, 0.0, 0.0, 0.0, 1.0],
                [1.0, -0.0, -0.0, 0.124994, -0.0, -0.999984, 0.005946, -0.002831, -0.0, -0.005946, -0.999982, -1.2e-05, 0.0, 0.0, 0.0, 1.0],
                [1.0, -0.0, -0.0, 0.124994, -0.0, -0.999984, 0.005946, -0.002831, -0.0, -0.005946, -0.999982, -1.2e-05, 0.0, 0.0, 0.0, 1.0],
                [1.0, -0.0, -0.0, 0.124994, -0.0, -0.999984, 0.005946, -0.002831, -0.0, -0.005946, -0.999982, -1.2e-05, 0.0, 0.0, 0.0, 1.0],
                [1.0, -0.0, -0.0, 0.124994, -0.0, -0.999984, 0.005946, -0.002831, -0.0, -0.005946, -0.999982, -1.2e-05, 0.0, 0.0, 0.0, 1.0],
                [1.0, -0.0, -0.0, 0.124994, -0.0, -0.999984, 0.005946, -0.002831, -0.0, -0.005946, -0.999982, -1.2e-05, 0.0, 0.0, 0.0, 1.0],
                [1.0, -0.0, -0.0, 0.124994, -0.0, -0.999984, 0.005946, -0.002831, -0.0, -0.005946, -0.999982, -1.2e-05, 0.0, 0.0, 0.0, 1.0],
                [1.0, -0.0, -0.0, 0.124994, -0.0, -0.999984, 0.005946, -0.002831, -0.0, -0.005946, -0.999982, -1.2e-05, 0.0, 0.0, 0.0, 1.0],
                [1.0, -0.0, -0.0, 0.124994, -0.0, -0.999984, 0.005946, -0.002831, -0.0, -0.005946, -0.999982, -1.2e-05, 0.0, 0.0, 0.0, 1.0],
                [1.0, -0.0, -0.0, 0.124994, -0.0, -0.999984, 0.005946, -0.002831, -0.0, -0.005946, -0.999982, -1.2e-05, 0.0, 0.0, 0.0, 1.0]
            ]
        },
        {
            "name": "IK-Leg_R",
            "time": [0.0, 1.0],
            "transform": [
                [1.0, 0.0, 1e-06, 0.0, -0.0, 0.999929, 0.011887, 0.374726, -1e-06, -0.011887, 0.999929, 0.0, 0.0, 0.0, 0.0, 1.0],
                [1.0, 0.0, 1e-06, 0.0, -0.0, 0.999929, 0.011887, 0.374726, -1e-06, -0.011887, 0.999929, 0.0, 0.0, 0.0, 0.0, 1.0]
            ]
        },
        {
            "name": "IK-Thigh_L",
            "time": [0.0, 0.0333, 0.0667, 0.1, 0.1333, 0.1667, 0.2, 0.2333, 0.2667, 0.3, 0.3333, 0.3667, 0.4, 0.4333, 0.4667, 0.5, 0.5333, 0.5667, 0.6, 0.6333, 0.6667, 0.7, 0.7333, 0.7667, 0.8, 0.8333, 0.8667, 0.9, 0.9333, 0.9667, 1.0],
            "transform": [
                [1.0, -0.0, -0.0, -0.125006, -0.0, -0.999984, 0.005917, -0.002831, -0.0, -0.005917, -0.999983, -1.2e-05, 0.0, 0.0, 0.0, 1.0],
                [1.0, -0.0, -0.0, -0.125006, -0.0, -0.999984, 0.005917, -0.002831, -0.0, -0.005917, -0.999983, -1.2e-05, 0.0, 0.0, 0.0, 1.0],
                [1.0, -0.0, -0.0, -0.125006, -0.0, -0.999984, 0.005917, -0.002831, -0.0, -0.005917, -0.999983, -1.2e-05, 0.0, 0.0, 0.0, 1.0],
                [1.0, -0.0, -0.0, -0.125006, -0.0, -0.999984, 0.005917, -0.002831, -0.0, -0.005917, -0.999983, -1.2e-05, 0.0, 0.0, 0.0, 1.0],
                [1.0, -0.0, -0.0, -0.125006, -0.0, -0.999984, 0.005917, -0.002831, -0.0, -0.005917, -0.999983, -1.2e-05, 0.0, 0.0, 0.0, 1.0],
                [1.0, -0.0, -0.0, -0.125006, -0.0, -0.999984, 0.005917, -0.002831, -0.0, -0.005917, -0.999983, -1.2e-05, 0.0, 0.0, 0.0, 1.0],
                [1.0, -0.0, -0.0, -0.125006, -0.0, -0.999984, 0.005917, -0.002831, -0.0, -0.005917, -0.999983, -1.2e-05, 0.0, 0.0, 0.0, 1.0],
                [1.0, -0.0, -0.0, -0.125006, -0.0, -0.999984, 0.005917, -0.002831, -0.0, -0.005917, -0.999983, -1.2e-05, 0.0, 0.0, 0.0, 1.0],
                [1.0, -0.0, -0.0, -0.125006, -0.0, -0.999984, 0.005917, -0.002831, -0.0, -0.005917, -0.999983, -1.2e-05, 0.0, 0.0, 0.0, 1.0],
                [1.0, -0.0, -0.0, -0.125006, -0.0, -0.999984, 0.005917, -0.002831, -0.0, -0.005917, -0.999983, -1.2e-05, 0.0, 0.0, 0.0, 1.0],
                [1.0, -0.0, -0.0, -0.125006, -0.0, -0.999984, 0.005917, -0.002831, -0.0, -0.005917, -0.999983, -1.2e-05, 0.0, 0.0, 0.0, 1.0],
                [1.0, -0.0, -0.0, -0.125006, -0.0, -0.999984, 0.005917, -0.002831, -0.0, -0.005917, -0.999983, -1.2e-05, 0.0, 0.0, 0.0, 1.0],
                [1.0, -0.0, -0.0, -0.125006, -0.0, -0.999984, 0.005917, -0.002831, -0.0, -0.005917, -0.999983, -1.2e-05, 0.0, 0.0, 0.0, 1.0],
                [1.0, -0.0, -0.0, -0.125006, -0.0, -0.999984, 0.005917, -0.002831, -0.0, -0.005917, -0.999983, -1.2e-05, 0.0, 0.0, 0.0, 1.0],
                [1.0, -0.0, -0.0, -0.125006, -0.0, -0.999984, 0.005917, -0.002831, -0.0, -0.005917, -0.999983, -1.2e-05, 0.0, 0.0, 0.0, 1.0],
                [1.0, -0.0, -0.0, -0.125006, -0.0, -0.999984, 0.005917, -0.002831, -0.0, -0.005917, -0.999983, -1.2e-05, 0.0, 0.0, 0.0, 1.0],
                [1.0, -0.0, -0.0, -0.125006, -0.0, -0.999984, 0.005917, -0.002831, -0.0, -0.005917, -0.999983, -1.2e-05, 0.0, 0.0, 0.0, 1.0],
                [1.0, -0.0, -0.0, -0.125006, -0.0, -0.999984, 0.005917, -0.002831, -0.0, -0.005917, -0.999983, -1.2e-05, 0.0, 0.0, 0.0, 1.0],
                [1.0, -0.0, -0.0, -0.125006, -0.0, -0.999984, 0.005917, -0.002831, -0.0, -0.005917, -0.999983, -1.2e-05, 0.0, 0.0, 0.0, 1.0],
                [1.0, -0.0, -0.0, -0.125006, -0.0, -0.999984, 0.005917, -0.002831, -0.0, -0.005917, -0.999983, -1.2e-05, 0.0, 0.0, 0.0, 1.0],
                [1.0, -0.0, -0.0, -0.125006, -0.0, -0.999984, 0.005917, -0.002831, -0.0, -0.005917, -0.999983, -1.2e-05, 0.0, 0.0, 0.0, 1.0],
                [1.0, -0.0, -0.0, -0.125006, -0.0, -0.999984, 0.005917, -0.002831, -0.0, -0.005917, -0.999983, -1.2e-05, 0.0, 0.0, 0.0, 1.0],
                [1.0, -0.0, -0.0, -0.125006, -0.0, -0.999984, 0.005917, -0.002831, -0.0, -0.005917, -0.999983, -1.2e-05, 0.0, 0.0, 0.0, 1.0],
                [1.0, -0.0, -0.0, -0.125006, -0.0, -0.999984, 0.005917, -0.002831, -0.0, -0.005917, -0.999983, -1.2e-05, 0.0, 0.0, 0.0, 1.0],
                [1.0, -0.0, -0.0, -0.125006, -0.0, -0.999984, 0.005917, -0.002831, -0.0, -0.005917, -0.999983, -1.2e-05, 0.0, 0.0, 0.0, 1.0],
                [1.0, -0.0, -0.0, -0.125006, -0.0, -0.999984, 0.005917, -0.002831, -0.0, -0.005917, -0.999983, -1.2e-05, 0.0, 0.0, 0.0, 1.0],
                [1.0, -0.0, -0.0, -0.125006, -0.0, -0.999984, 0.005917, -0.002831, -0.0, -0.005917, -0.999983, -1.2e-05, 0.0, 0.0, 0.0, 1.0],
                [1.0, -0.0, -0.0, -0.125006, -0.0, -0.999984, 0.005917, -0.002831, -0.0, -0.005917, -0.999983, -1.2e-05, 0.0, 0.0, 0.0, 1.0],
                [1.0, -0.0, -0.0, -0.125006, -0.0, -0.999984, 0.005917, -0.002831, -0.0, -0.005917, -0.999983, -1.2e-05, 0.0, 0.0, 0.0, 1.0],
                [1.0, -0.0, -0.0, -0.125006, -0.0, -0.999984, 0.005917, -0.002831, -0.0, -0.005917, -0.999983, -1.2e-05, 0.0, 0.0, 0.0, 1.0],
                [1.0, -0.0, -0.0, -0.125006, -0.0, -0.999984, 0.005917, -0.002831, -0.0, -0.005917, -0.999983, -1.2e-05, 0.0, 0.0, 0.0, 1.0]
            ]
        }
    ]
}